{
  "plan_id": "H4739_001_0",
  "scraped_at": "2025-12-09T02:08:36.333221",
  "url": "https://www.medicare.gov/plan-compare/#/plan-details/2026-H4739-001-0?year=2026&lang=en",
  "raw_content": "An official website of the United States government\nHere's how you know\n\n\nMenu\nBack to search results\nFirst Choice VIP Care (HMO D-SNP)\nFirst Choice VIP Care (HMO D-SNP)\nPlan type: Medicare Advantage with drug coverage\nSNP type: Dual Eligible\nPlan ID: H4739-001-0\nPrint\nPlan website\nNon-members:\nphone number\n1-833-961-3723\nMembers:\nphone number\n1-888-996-0499\nEnroll\nWhat you'll pay\nTotal monthly premium\n$0.00\nHealth deductible\n$0.00\nPrimary doctor\n$0\ncopay\nOverview\nPREMIUMS\nTotal monthly premium\n$0.00\nHealth premium\n$0.00\nDrug premium\n$0.00\nStandard Part B premium\nWhat's the standard Part B premium?\n$202.90\nPart B premium reduction\nWhat's the Part B premium reduction?\nNot offered\nDEDUCTIBLES\nThe amount you must pay each year before your plan starts to pay for covered services or drugs.\nHealth deductible\n$0.00\nDrug deductible\n$615.00\nMAXIMUM YOU PAY FOR HEALTH SERVICES\nMaximum you pay for health services\n$9,250 In-network\nCONTACT INFORMATION\nPlan address\n1705 Markley St.\nSuite 210\nNorristown, PA 19401\nBenefits & Costs\nDOCTOR SERVICES\nView Provider Network Directory\nPrimary doctor visit\nIn-network: $0 copay\nSpecialist visit\nIn-network: $0 copay\nTESTS, LABS, & IMAGING\nDiagnostic tests & procedures\nIn-network: $0 copay\nLimits apply\n(Tests, labs, & imaging|Diagnostic tests & procedures)\nLab services\nIn-network: $0 copay\nLimits apply\n(Tests, labs, & imaging|Lab services)\nDiagnostic radiology services (like MRI)\nIn-network: $0 copay\nLimits apply\n(Tests, labs, & imaging|Diagnostic radiology services (like MRI))\nOutpatient x-rays\nIn-network: $0 copay\nLimits apply\n(Tests, labs, & imaging|Outpatient x-rays)\nEmergency care\n$0 copay\nUrgent care\n$0 copay\nHOSPITAL SERVICES\nInpatient hospital coverage\nTier 1\n$0 per day for days 1-2\n$0 per day for days 3-90\n$0 per stay\nLimits apply\n(Hospital services|Inpatient hospital coverage)\nOutpatient hospital coverage\nIn-network: $0 copay\nLimits apply\n(Hospital services|Outpatient hospital coverage)\nSKILLED NURSING FACILITY\nSkilled nursing facility\nTier 1\n$0 per day for days 1-20\n$0 per day for days 21-100\nLimits apply\n(Skilled nursing facility|Skilled nursing facility)\nPREVENTIVE SERVICES\nHealth care to prevent illness or detect illness at an early stage, when treatment is likely to work best (like Pap tests, flu shots, and screening mammograms).\nLearn more about your costs for preventive services\nPreventive services\nIn-network: $0 copay\nAMBULANCE\nGround ambulance\nIn-network: $0 copay\nLimits apply\n(Ambulance|Ground ambulance)\nTHERAPY SERVICES\nOccupational therapy visit\nIn-network: $0 copay\nLimits apply\n(Therapy services|Occupational therapy visit)\nPhysical therapy & speech & language therapy visit\nIn-network: $0 copay\nLimits apply\n(Therapy services|Physical therapy & speech & language therapy visit)\nView more benefits & costs\n\n\n\n\n\n\n\n\n\nDrug Coverage\nSee if there's help to lower costs for drugs you take.\nPHARMACIES\nAdd pharmacies to get better cost estimates\nYour drug costs can change depending on your plan and pharmacy. Adding pharmacies to your account can give you better out-of-pocket cost estimates when comparing plans.\nAdd Pharmacies\nCheck the network status of each pharmacy on your list. You can change pharmacies at any time to find lower costs for drugs.\nHow do pharmacy networks affect what I pay?\nChange Pharmacies\nCOSTS BY DRUG TIER\nEach plan has a list of drugs they cover (called a \u201cformulary\u201d). Drugs on the list can be grouped into tiers with different cost levels. Some plans don\u2019t use tiers. Below is what you\u2019ll pay for drugs in each tier, based on your coverage phase.\nLearn more about drug tiers.\nTIER DRUG COST FOR\nStandard retail pharmacy drug cost for 1 month\nChange\nCOSTS BY DRUG TIER - STANDARD RETAIL PHARMACY DRUG COST FOR 1 MONTH\nPreferred Generic\nInitial coverage phase\n25% coinsurance\nCatastrophic coverage phase\n$0 copay\nGeneric\nInitial coverage phase\n25% coinsurance\nCatastrophic coverage phase\n$0 copay\nPreferred Brand\nInitial coverage phase\n25% coinsurance\nCatastrophic coverage phase\n$0 copay\nNon-Preferred Drug\nInitial coverage phase\n25% coinsurance\nCatastrophic coverage phase\n$0 copay\nSpecialty Tier\nInitial coverage phase\n25% coinsurance\nCatastrophic coverage phase\n$0 copay\nSelect Care Drugs\nInitial coverage phase\n$0.00 copay\nCatastrophic coverage phase\n$0 copay\nPART B DRUGS\nThese are drugs you usually get at a doctor's office or hospital outpatient setting, like the flu shot, chemotherapy, or other shots.\nPart B insulin\nIn-network: $0 copay\nLimits apply\n(Part B drugs|Part B insulin)\nChemotherapy drugs\nIn-network: $0 copay\nLimits apply\n(Part B drugs|Chemotherapy drugs)\nOther Part B drugs\nIn-network: $0 copay\nLimits apply\n(Part B drugs|Other Part B drugs)\nExtra Benefits\nHEARING\nHearing exam\nIn-network: $0 copay\nLimits apply\n(Hearing|Hearing exam)\nFitting/evaluation\nIn-network: $0 copay\nHearing aids - prescription\nIn-network: $0 copay\nLimits apply\n(Hearing|Hearing aids - prescription)\nHearing aids - over the counter\nNot covered\nPREVENTIVE DENTAL\nCare to prevent or find problems with your teeth and gums.\nOral exam\nIn-network: $0 copay\nLimits apply\n(Preventive dental|Oral exam)\nCleaning\nIn-network: $0 copay\nLimits apply\n(Preventive dental|Cleaning)\nFluoride treatment\nIn-network: $0 copay\nLimits apply\n(Preventive dental|Fluoride treatment)\nDental x-rays\nIn-network: $0 copay\nLimits apply\n(Preventive dental|Dental x-rays)\nCOMPREHENSIVE DENTAL\nCare to maintain or treat problems with your teeth and gums.\nRestorative services\nIn-network: $0 copay\nLimits apply\n(Comprehensive dental|Restorative services)\nEndodontics\nIn-network: $0 copay\nLimits apply\n(Comprehensive dental|Endodontics)\nPeriodontics\nIn-network: $0 copay\nLimits apply\n(Comprehensive dental|Periodontics)\nProsthodontics, removable\nIn-network: $0 copay\nLimits apply\n(Comprehensive dental|Prosthodontics, removable)\nProsthodontics, fixed\nIn-network: $0 copay\nLimits apply\n(Comprehensive dental|Prosthodontics, fixed)\nMaxillofacial prosthetics\nIn-network: $0 copay\nLimits apply\n(Comprehensive dental|Maxillofacial prosthetics)\nImplant services\nIn-network: $0 copay\nLimits apply\n(Comprehensive dental|Implant services)\nOral and maxillofacial surgery\nIn-network: $0 copay\nLimits apply\n(Comprehensive dental|Oral and maxillofacial surgery)\nOrthodontics\nNot covered\nAdjunctive general services\nNot covered\nVISION\nRoutine eye exam\nIn-network: $0 copay\nLimits apply\n(Vision|Routine eye exam)\nContact lenses\nIn-network: $0 copay\nLimits apply\n(Vision|Contact lenses)\nEyeglasses (frames & lenses)\nIn-network: $0 copay\nLimits apply\n(Vision|Eyeglasses (frames & lenses))\nEyeglass frames only\nNot covered\nEyeglass lenses only\nNot covered\nUpgrades\nNot covered\nCollapse more extra benefits\nMEDICALLY-APPROVED NON-OPIOID PAIN MANAGEMENT SERVICES\nChiropractic services\nIn-network: $0 copay\nLimits apply\n(Chiropractic services)\nPlan limits - There may be limits, like the number of times you can use the item or service or how much the plan will cover. Contact the plan for details.\nAcupuncture\nIn-network: $0 copay\nLimits apply\n(Acupuncture)\nPlan limits - There may be limits, like the number of times you can use the item or service or how much the plan will cover. Contact the plan for details.\nMassage therapy\nNot covered\nAlternative therapies\nNot covered\nMORE BENEFITS\nHealth Education\nNot covered\nCounseling Services\nNot covered\nSupport for Caregivers of Enrollees\nNot covered\nPersonal Emergency Response System (PERS)\nIn-network: $0 copay\nLimits apply\n(Preventive services|Personal Emergency Response System (PERS))\nPlan limits - There may be limits, like the number of times you can use the item or service or how much the plan will cover. Contact the plan for details.\nFitness benefit\nIn-network: $0 copay\nLimits apply\n(Preventive services|Fitness benefit)\nPlan limits - There may be limits, like the number of times you can use the item or service or how much the plan will cover. Contact the plan for details.\nTransportation services for non-emergency care: Any health-related locations\nNot covered\nTransportation services for non-emergency care: Plan-approved locations\nIn-network: $0 copay\nLimits apply\n(Transportation|Transportation services for non-emergency care: Plan-approved locations)\nPlan limits - There may be limits, like the number of times you can use the item or service or how much the plan will cover. Contact the plan for details.\nOver the counter drug benefits\nIn-network: $0 copay\nLimits apply\n(Other services|Over the counter drug benefits)\nPlan limits - There may be limits, like the number of times you can use the item or service or how much the plan will cover. Contact the plan for details.\nIn-home support services\nNot covered\nHome and bathroom safety devices\nNot covered\nMeals for short duration\nIn-network: $0 copay\nLimits apply\n(Other services|Meals for short duration)\nPhysician Referral Required - A process through which the enrollee\u2019s primary care physician or other network physician (depending on the plan policy) permits or instructs the enrollee to obtain an item or service from another physician or other provider type.\nPlan limits - There may be limits, like the number of times you can use the item or service or how much the plan will cover. Contact the plan for details.\nAnnual physical exams\nNot covered\nTelehealth\nNot covered\nWorldwide emergency\n$0 copay\nLimits apply\n(Emergency care|Worldwide emergency)\nPlan limits - There may be limits, like the number of times you can use the item or service or how much the plan will cover. Contact the plan for details.\nPost discharge in-home medication reconciliation\nNot covered\nRe-admission prevention\nNot covered\nWigs for hair loss related to chemotherapy\nNot covered\nWeight management programs\nNot covered\nAdult day health services\nNot covered\nHome-based palliative care\nNot covered\nSPECIAL BENEFITS\nYou may get these benefits if you have a qualifying chronic condition or other factors. Contact the plan to see if you qualify before you enroll.\nFood & produce\nIn-network: $0 copay\nLimits apply\n(Chronic illness services|Food & produce)\nPlan limits - There may be limits, like the number of times you can use the item or service or how much the plan will cover. Contact the plan for details.\nMeals\nNot covered\nPest control\nIn-network: $0 copay\nLimits apply\n(Chronic illness services|Pest control)\nPlan limits - There may be limits, like the number of times you can use the item or service or how much the plan will cover. Contact the plan for details.\nTransportation for non-medical needs\nNot covered\nTransportation services for non-emergency care: Plan-approved locations\nNot covered\nIndoor air quality equipment and services\nNot covered\nSocial needs benefit\nNot covered\nComplementary therapies\nNot covered\nServices supporting self-direction\nNot covered\nStructural home modifications\nNot covered\nGeneral supports for living\nIn-network: $0 copay\nLimits apply\n(Chronic illness services|General supports for living)\nPlan limits - There may be limits, like the number of times you can use the item or service or how much the plan will cover. Contact the plan for details.\nReduced cost sharing for qualifying individuals\nNot covered  \nStar Ratings\nExpand All Ratings\nOverall star rating\nOverall rating is based on the categories below.\nNot enough data available\nHealth plan star rating\nSummary rating of health plan quality\nNot enough data available\nDrug plan star rating\nSummary rating of drug plan quality\nstars\nProviders\nView Provider Network Directory\nFind participating providers\nAdd your providers to find out if they participate in this plan.\nAdd Provider\nAbout Medicare\nNondiscrimination/Accessibility\nPrivacy Policy\nPrivacy Setting\nLinking Policy\nUsing this site\nPlain Writing\nA federal government website managed and paid for by the U.S. Centers for Medicare & Medicaid Services.\n7500 Security Boulevard, Baltimore, MD 21244\n\nGive Feedback",
  "plan_info": {
    "name": "First Choice VIP Care (HMO D-SNP)\nFirst Choice VIP Care (HMO D-SNP)",
    "found": true,
    "organization": "First Choice VIP",
    "type": "Medicare Advantage with drug coverage",
    "id": "H4739-001-0"
  },
  "premiums": {
    "Total monthly premium": "$0.00",
    "Health premium": "$0.00",
    "Drug premium": "$0.00",
    "Part B premium reduction": "$What's the Part B premium reduction?"
  },
  "deductibles": {
    "Health deductible": "$0.00",
    "Drug deductible": "$615.00"
  },
  "maximum_out_of_pocket": {
    "Maximum you pay for health services": "$9,250 In-network"
  },
  "contact_info": {
    "Plan address": "1705 Markley St.\nSuite 210"
  },
  "benefits": {
    "Doctor Services": {
      "Primary doctor visit": "In-network: $0 copay",
      "Specialist visit": "In-network: $0 copay",
      "Diagnostic tests & procedures": "In-network: $0 copay",
      "Lab services": "In-network: $0 copay",
      "Diagnostic radiology services (like MRI)": "In-network: $0 copay",
      "Outpatient x-rays": "In-network: $0 copay",
      "Emergency care": "$0 copay",
      "Urgent care": "$0 copay"
    },
    "Tests, Labs, & Imaging": {
      "Diagnostic tests & procedures": "In-network: $0 copay",
      "Lab services": "In-network: $0 copay",
      "Diagnostic radiology services (like MRI)": "In-network: $0 copay",
      "Outpatient x-rays": "In-network: $0 copay",
      "Emergency care": "$0 copay",
      "Urgent care": "$0 copay"
    },
    "Hospital Services": {
      "Inpatient hospital coverage": "Tier 1",
      "$0 per day for days 1-2": "$0 per day for days 3-90",
      "Outpatient hospital coverage": "In-network: $0 copay"
    },
    "Preventive Services": {
      "Preventive services": "In-network: $0 copay"
    },
    "Vision": {
      "Routine eye exam": "In-network: $0 copay",
      "Contact lenses": "In-network: $0 copay",
      "Eyeglasses (frames & lenses)": "In-network: $0 copay",
      "Eyeglass frames only": "Not covered",
      "Eyeglass lenses only": "Not covered",
      "Upgrades": "Not covered",
      "Chiropractic services": "In-network: $0 copay",
      "Acupuncture": "In-network: $0 copay",
      "Massage therapy": "Not covered",
      "Alternative therapies": "Not covered"
    },
    "Hearing": {
      "Hearing exam": "In-network: $0 copay",
      "Fitting/evaluation": "In-network: $0 copay",
      "Hearing aids - prescription": "In-network: $0 copay",
      "Hearing aids - over the counter": "Not covered"
    },
    "Preventive Dental": {
      "Oral exam": "In-network: $0 copay",
      "Cleaning": "In-network: $0 copay",
      "Fluoride treatment": "In-network: $0 copay",
      "Dental x-rays": "In-network: $0 copay"
    },
    "Comprehensive Dental": {
      "Restorative services": "In-network: $0 copay",
      "Endodontics": "In-network: $0 copay",
      "Periodontics": "In-network: $0 copay",
      "Prosthodontics, removable": "In-network: $0 copay",
      "Prosthodontics, fixed": "In-network: $0 copay",
      "Maxillofacial prosthetics": "In-network: $0 copay",
      "Implant services": "In-network: $0 copay",
      "Oral and maxillofacial surgery": "In-network: $0 copay",
      "Orthodontics": "Not covered",
      "Adjunctive general services": "Not covered"
    },
    "Dental": {
      "Oral exam": "In-network: $0 copay",
      "Cleaning": "In-network: $0 copay",
      "Fluoride treatment": "In-network: $0 copay",
      "Dental x-rays": "In-network: $0 copay"
    },
    "Skilled Nursing Facility": {
      "Skilled nursing facility": "Tier 1",
      "$0 per day for days 1-20": "$0 per day for days 21-100"
    }
  }
}