{
  "plan_id": "H0710_053_0",
  "scraped_at": "2025-12-09T01:57:00.955822",
  "url": "https://www.medicare.gov/plan-compare/#/plan-details/2026-H0710-053-0?year=2026&lang=en",
  "raw_content": "An official website of the United States government\nHere's how you know\n\n\nMenu\nBack to search results\nUHC Nursing Home Plan SC-F001 (PPO I-SNP)\nUnitedHealthcare\nPlan type: Medicare Advantage with drug coverage\nSNP type: Institutional\nPlan ID: H0710-053-0\nPrint\nPlan website\nNon-members:\nphone number\n1-888-834-3721\nMembers:\nphone number\n1-877-370-4892\nContact plan to check eligibility\nWhat you'll pay\nTotal monthly premium\n$35.70\nHealth deductible\n$0.00\nPrimary doctor\n0%-20%\ncoinsurance\nOverview\nPREMIUMS\nTotal monthly premium\n$35.70\nHealth premium\n$0.00\nDrug premium\n$35.70\nStandard Part B premium\nWhat's the standard Part B premium?\n$202.90\nPart B premium reduction\nWhat's the Part B premium reduction?\n\u2212$0.60 reduction\nDEDUCTIBLES\nThe amount you must pay each year before your plan starts to pay for covered services or drugs.\nHealth deductible\n$0.00\nDrug deductible\n$615.00\nMAXIMUM YOU PAY FOR HEALTH SERVICES\nMaximum you pay for health services\n$13,900 In and Out-of-network\n$9,250 In-network\nCONTACT INFORMATION\nPlan address\nP.O. Box 30770\nSalt Lake City, UT 84130\nBenefits & Costs\nDOCTOR SERVICES\nView Provider Network Directory\nPrimary doctor visit\nIn-network: 0%-20% coinsurance\nOut-of-network: 30% coinsurance\nSpecialist visit\nIn-network: 0%-20% coinsurance\nOut-of-network: 30% coinsurance\nLimits apply\n(Doctor services|Specialist visit)\nTESTS, LABS, & IMAGING\nDiagnostic tests & procedures\nIn-network: 20% coinsurance\nOut-of-network: 30% coinsurance\nLimits apply\n(Tests, labs, & imaging|Diagnostic tests & procedures)\nLab services\nIn-network: $0 copay\nOut-of-network: $0 copay\nLimits apply\n(Tests, labs, & imaging|Lab services)\nDiagnostic radiology services (like MRI)\nIn-network: 0%-20% coinsurance\nOut-of-network: 30% coinsurance\nLimits apply\n(Tests, labs, & imaging|Diagnostic radiology services (like MRI))\nOutpatient x-rays\nIn-network: 20% coinsurance\nOut-of-network: 30% coinsurance\nLimits apply\n(Tests, labs, & imaging|Outpatient x-rays)\nEmergency care\n$115 copay\nUrgent care\n$0-$40 copay\nHOSPITAL SERVICES\nInpatient hospital coverage\nIn-network:\nTier 1\n$2,025 per stay\nOut-of-network:\n$2,025 per stay\nLimits apply\n(Hospital services|Inpatient hospital coverage)\nOutpatient hospital coverage\nIn-network: 0%-20% coinsurance\nOut-of-network: 30% coinsurance\nLimits apply\n(Hospital services|Outpatient hospital coverage)\nSKILLED NURSING FACILITY\nSkilled nursing facility\nIn-network:\nTier 1\n$0 per day for days 1-100\nOut-of-network:\n30% per stay\nLimits apply\n(Skilled nursing facility|Skilled nursing facility)\nPREVENTIVE SERVICES\nHealth care to prevent illness or detect illness at an early stage, when treatment is likely to work best (like Pap tests, flu shots, and screening mammograms).\nLearn more about your costs for preventive services\nPreventive services\nIn-network: $0 copay\nOut-of-network: 0%-30% coinsurance\nAMBULANCE\nGround ambulance\nIn-network: 20% coinsurance\nOut-of-network: 20% coinsurance\nLimits apply\n(Ambulance|Ground ambulance)\nTHERAPY SERVICES\nOccupational therapy visit\nIn-network: 20% coinsurance\nOut-of-network: 30% coinsurance\nLimits apply\n(Therapy services|Occupational therapy visit)\nPhysical therapy & speech & language therapy visit\nIn-network: 20% coinsurance\nOut-of-network: 30% coinsurance\nLimits apply\n(Therapy services|Physical therapy & speech & language therapy visit)\nView more benefits & costs\n\n\n\n\n\n\n\n\n\nDrug Coverage\nSee if there's help to lower costs for drugs you take.\nPHARMACIES\nAdd pharmacies to get better cost estimates\nYour drug costs can change depending on your plan and pharmacy. Adding pharmacies to your account can give you better out-of-pocket cost estimates when comparing plans.\nAdd Pharmacies\nCheck the network status of each pharmacy on your list. You can change pharmacies at any time to find lower costs for drugs.\nHow do pharmacy networks affect what I pay?\nChange Pharmacies\nCOSTS BY DRUG TIER\nEach plan has a list of drugs they cover (called a \u201cformulary\u201d). Drugs on the list can be grouped into tiers with different cost levels. Some plans don\u2019t use tiers. Below is what you\u2019ll pay for drugs in each tier, based on your coverage phase.\nLearn more about drug tiers.\nTIER DRUG COST FOR\nStandard retail pharmacy drug cost for 1 month\nChange\nCOSTS BY DRUG TIER - STANDARD RETAIL PHARMACY DRUG COST FOR 1 MONTH\nBrand-name drugs\nInitial coverage phase\n25% coinsurance\nCatastrophic coverage phase\n0% coinsurance\nGeneric drugs\nInitial coverage phase\n25% coinsurance\nCatastrophic coverage phase\n0% coinsurance\nPART B DRUGS\nThese are drugs you usually get at a doctor's office or hospital outpatient setting, like the flu shot, chemotherapy, or other shots.\nPart B insulin\nIn-network: 0%-20% coinsurance\nOut-of-network: 30% coinsurance\nLimits apply\n(Part B drugs|Part B insulin)\nChemotherapy drugs\nIn-network: 0%-20% coinsurance\nOut-of-network: 30% coinsurance\nLimits apply\n(Part B drugs|Chemotherapy drugs)\nOther Part B drugs\nIn-network: 0%-20% coinsurance\nOut-of-network: 0%-30% coinsurance\nLimits apply\n(Part B drugs|Other Part B drugs)\nExtra Benefits\nHEARING\nHearing exam\nIn-network: $0 copay\nOut-of-network: 30% coinsurance\nLimits apply\n(Hearing|Hearing exam)\nFitting/evaluation\nNot covered\nHearing aids - prescription\nIn-network: $0 copay\nOut-of-network: $0 copay\nLimits apply\n(Hearing|Hearing aids - prescription)\nHearing aids - over the counter\nIn-network: $0 copay\nOut-of-network: $0 copay\nLimits apply\n(Hearing|Hearing aids - over the counter)\nPREVENTIVE DENTAL\nCare to prevent or find problems with your teeth and gums.\nOral exam\nIn-network: $0 copay\nOut-of-network: $0 copay\nLimits apply\n(Preventive dental|Oral exam)\nCleaning\nIn-network: $0 copay\nOut-of-network: $0 copay\nLimits apply\n(Preventive dental|Cleaning)\nFluoride treatment\nIn-network: $0 copay\nOut-of-network: $0 copay\nLimits apply\n(Preventive dental|Fluoride treatment)\nDental x-rays\nIn-network: $0 copay\nOut-of-network: $0 copay\nLimits apply\n(Preventive dental|Dental x-rays)\nCOMPREHENSIVE DENTAL\nCare to maintain or treat problems with your teeth and gums.\nRestorative services\nNot covered\nEndodontics\nNot covered\nPeriodontics\nNot covered\nProsthodontics, removable\nNot covered\nProsthodontics, fixed\nNot covered\nMaxillofacial prosthetics\nNot covered\nImplant services\nNot covered\nOral and maxillofacial surgery\nNot covered\nOrthodontics\nNot covered\nAdjunctive general services\nNot covered\nVISION\nRoutine eye exam\nIn-network: $0 copay\nOut-of-network: 30% coinsurance\nLimits apply\n(Vision|Routine eye exam)\nContact lenses\nIn-network: $0 copay\nOut-of-network: $0 copay\nLimits apply\n(Vision|Contact lenses)\nEyeglasses (frames & lenses)\nNot covered\nEyeglass frames only\nIn-network: $0 copay\nOut-of-network: $0 copay\nLimits apply\n(Vision|Eyeglass frames only)\nEyeglass lenses only\nIn-network: $0 copay\nOut-of-network: $0 copay\nLimits apply\n(Vision|Eyeglass lenses only)\nUpgrades\nNot covered\nCollapse more extra benefits\nMEDICALLY-APPROVED NON-OPIOID PAIN MANAGEMENT SERVICES\nChiropractic services\nNot covered\nAcupuncture\nNot covered\nMassage therapy\nNot covered\nAlternative therapies\nNot covered\nMORE BENEFITS\nHealth Education\nNot covered\nCounseling Services\nNot covered\nSupport for Caregivers of Enrollees\nNot covered\nPersonal Emergency Response System (PERS)\nNot covered\nFitness benefit\nNot covered\nTransportation services for non-emergency care: Any health-related locations\nNot covered\nTransportation services for non-emergency care: Plan-approved locations\nIn-network: $0 copay\nOut-of-network: 75% coinsurance\nLimits apply\n(Transportation|Transportation services for non-emergency care: Plan-approved locations)\nPlan limits - There may be limits, like the number of times you can use the item or service or how much the plan will cover. Contact the plan for details.\nOver the counter drug benefits\nIn-network: $0 copay\nOut-of-network: $0 copay\nLimits apply\n(Other services|Over the counter drug benefits)\nPlan limits - There may be limits, like the number of times you can use the item or service or how much the plan will cover. Contact the plan for details.\nIn-home support services\nNot covered\nHome and bathroom safety devices\nIn-network: $0 copay\nOut-of-network: $0 copay\nLimits apply\n(Preventive services|Home and bathroom safety devices)\nPlan limits - There may be limits, like the number of times you can use the item or service or how much the plan will cover. Contact the plan for details.\nMeals for short duration\nNot covered\nAnnual physical exams\nIn-network: $0 copay\nLimits apply\n(Preventive services|Annual physical exams)\nPlan limits - There may be limits, like the number of times you can use the item or service or how much the plan will cover. Contact the plan for details.\nTelehealth\nIn-network: $0 copay\nLimits apply\n(Professional services|Telehealth)\nPlan limits - There may be limits, like the number of times you can use the item or service or how much the plan will cover. Contact the plan for details.\nWorldwide emergency\nNot covered\nPost discharge in-home medication reconciliation\nNot covered\nRe-admission prevention\nNot covered\nWigs for hair loss related to chemotherapy\nNot covered\nWeight management programs\nNot covered\nAdult day health services\nNot covered\nHome-based palliative care\nNot covered\nStar Ratings\nExpand All Ratings\nOverall star rating\nOverall rating is based on the categories below.\nstars\nHealth plan star rating\nSummary rating of health plan quality\nstars\nDrug plan star rating\nSummary rating of drug plan quality\nstars\nProviders\nView Provider Network Directory\nFind participating providers\nAdd your providers to find out if they participate in this plan.\nAdd Provider\nAbout Medicare\nNondiscrimination/Accessibility\nPrivacy Policy\nPrivacy Setting\nLinking Policy\nUsing this site\nPlain Writing\nA federal government website managed and paid for by the U.S. Centers for Medicare & Medicaid Services.\n7500 Security Boulevard, Baltimore, MD 21244\n\nGive Feedback",
  "plan_info": {
    "name": "UHC Nursing Home Plan SC-F001 (PPO I-SNP)\nUnitedHealthcare",
    "found": true,
    "organization": "UnitedHealthcare",
    "type": "Medicare Advantage with drug coverage",
    "id": "H0710-053-0"
  },
  "premiums": {
    "Total monthly premium": "$35.70",
    "Health premium": "$0.00",
    "Drug premium": "$35.70",
    "Part B premium reduction": "$What's the Part B premium reduction?"
  },
  "deductibles": {
    "Health deductible": "$0.00",
    "Drug deductible": "$615.00"
  },
  "maximum_out_of_pocket": {
    "Maximum you pay for health services": "$13,900 In and Out-of-network"
  },
  "contact_info": {
    "Plan address": "P.O. Box 30770\nSalt Lake City, UT 84130"
  },
  "benefits": {
    "Doctor Services": {
      "Primary doctor visit": "In-network: 0%-20% coinsurance",
      "Specialist visit": "In-network: 0%-20% coinsurance",
      "Diagnostic tests & procedures": "In-network: 20% coinsurance",
      "Lab services": "In-network: $0 copay",
      "Diagnostic radiology services (like MRI)": "In-network: 0%-20% coinsurance",
      "Outpatient x-rays": "In-network: 20% coinsurance",
      "Emergency care": "$115 copay",
      "Urgent care": "$0-$40 copay"
    },
    "Tests, Labs, & Imaging": {
      "Diagnostic tests & procedures": "In-network: 20% coinsurance",
      "Lab services": "In-network: $0 copay",
      "Diagnostic radiology services (like MRI)": "In-network: 0%-20% coinsurance",
      "Outpatient x-rays": "In-network: 20% coinsurance",
      "Emergency care": "$115 copay",
      "Urgent care": "$0-$40 copay"
    },
    "Hospital Services": {
      "Inpatient hospital coverage": "In-network:",
      "Tier 1": "$2,025 per stay",
      "Out-of-network:": "$2,025 per stay",
      "Outpatient hospital coverage": "In-network: 0%-20% coinsurance"
    },
    "Preventive Services": {
      "Preventive services": "In-network: $0 copay"
    },
    "Vision": {
      "Routine eye exam": "In-network: $0 copay",
      "Contact lenses": "In-network: $0 copay",
      "Eyeglasses (frames & lenses)": "Not covered",
      "Eyeglass frames only": "In-network: $0 copay",
      "Eyeglass lenses only": "In-network: $0 copay",
      "Upgrades": "Not covered",
      "Chiropractic services": "Not covered",
      "Acupuncture": "Not covered",
      "Massage therapy": "Not covered",
      "Alternative therapies": "Not covered"
    },
    "Hearing": {
      "Hearing exam": "In-network: $0 copay",
      "Fitting/evaluation": "Not covered",
      "Hearing aids - prescription": "In-network: $0 copay",
      "Hearing aids - over the counter": "In-network: $0 copay"
    },
    "Preventive Dental": {
      "Oral exam": "In-network: $0 copay",
      "Cleaning": "In-network: $0 copay",
      "Fluoride treatment": "In-network: $0 copay",
      "Dental x-rays": "In-network: $0 copay"
    },
    "Comprehensive Dental": {
      "Restorative services": "Not covered",
      "Endodontics": "Not covered",
      "Periodontics": "Not covered",
      "Prosthodontics, removable": "Not covered",
      "Prosthodontics, fixed": "Not covered",
      "Maxillofacial prosthetics": "Not covered",
      "Implant services": "Not covered",
      "Oral and maxillofacial surgery": "Not covered",
      "Orthodontics": "Not covered",
      "Adjunctive general services": "Not covered"
    },
    "Dental": {
      "Oral exam": "In-network: $0 copay",
      "Cleaning": "In-network: $0 copay",
      "Fluoride treatment": "In-network: $0 copay",
      "Dental x-rays": "In-network: $0 copay"
    },
    "Skilled Nursing Facility": {
      "Skilled nursing facility": "In-network:",
      "Tier 1": "$0 per day for days 1-100"
    }
  }
}