{
  "plan_id": "H2001_076_0",
  "scraped_at": "2025-12-09T02:00:29.219241",
  "url": "https://www.medicare.gov/plan-compare/#/plan-details/2026-H2001-076-0?year=2026&lang=en",
  "raw_content": "An official website of the United States government\nHere's how you know\n\n\nMenu\nBack to search results\nUHC Complete Care Support SC-7 (PPO C-SNP)\nUnitedHealthcare\nPlan type: Medicare Advantage with drug coverage\nSNP type: Chronic Condition\nPlan ID: H2001-076-0\nPrint\nPlan website\nNon-members:\nphone number\n1-800-555-5757\nMembers:\nphone number\n1-877-370-4892\nEnroll\nWhat you'll pay\nTotal monthly premium\n$35.70\nHealth deductible\n$0.00\nPrimary doctor\n$0\ncopay\nOverview\nPREMIUMS\nTotal monthly premium\n$35.70\nHealth premium\n$0.00\nDrug premium\n$35.70\nStandard Part B premium\nWhat's the standard Part B premium?\n$202.90\nPart B premium reduction\nWhat's the Part B premium reduction?\n\u2212$0.80 reduction\nDEDUCTIBLES\nThe amount you must pay each year before your plan starts to pay for covered services or drugs.\nHealth deductible\n$0.00\nDrug deductible\n$615.00\nMAXIMUM YOU PAY FOR HEALTH SERVICES\nMaximum you pay for health services\n$10,100 In and Out-of-network\n$6,700 In-network\nCONTACT INFORMATION\nPlan address\nP.O. Box 30770\nSalt Lake City, UT 84130\nBenefits & Costs\nDOCTOR SERVICES\nView Provider Network Directory\nPrimary doctor visit\nIn-network: $0 copay\nOut-of-network: $20 copay\nSpecialist visit\nIn-network: $0-$40 copay\nOut-of-network: $65 copay\nLimits apply\n(Doctor services|Specialist visit)\nTESTS, LABS, & IMAGING\nDiagnostic tests & procedures\nIn-network: $35 copay\nOut-of-network: 40% coinsurance\nLimits apply\n(Tests, labs, & imaging|Diagnostic tests & procedures)\nLab services\nIn-network: $0 copay\nOut-of-network: $0 copay\nLimits apply\n(Tests, labs, & imaging|Lab services)\nDiagnostic radiology services (like MRI)\nIn-network: $0-$260 copay\nOut-of-network: 40% coinsurance\nLimits apply\n(Tests, labs, & imaging|Diagnostic radiology services (like MRI))\nOutpatient x-rays\nIn-network: $25 copay\nOut-of-network: $50 copay\nLimits apply\n(Tests, labs, & imaging|Outpatient x-rays)\nEmergency care\n$130 copay\nUrgent care\n$0-$50 copay\nHOSPITAL SERVICES\nInpatient hospital coverage\nIn-network:\nTier 1\n$455 per day for days 1-6\n$0 per day for days 7-90\n$0 per stay\nOut-of-network:\n$560 per day for days 1-19\n$0 per day for days 20-999\n$0 per stay\nLimits apply\n(Hospital services|Inpatient hospital coverage)\nOutpatient hospital coverage\nIn-network: $0-$455 copay\nOut-of-network: $560 copay\nLimits apply\n(Hospital services|Outpatient hospital coverage)\nSKILLED NURSING FACILITY\nSkilled nursing facility\nIn-network:\nTier 1\n$0 per day for days 1-20\n$218 per day for days 21-100\nOut-of-network:\n$250 per day for days 1-100\n$0 per stay\nLimits apply\n(Skilled nursing facility|Skilled nursing facility)\nPREVENTIVE SERVICES\nHealth care to prevent illness or detect illness at an early stage, when treatment is likely to work best (like Pap tests, flu shots, and screening mammograms).\nLearn more about your costs for preventive services\nPreventive services\nIn-network: $0 copay\nOut-of-network: 0%-40% coinsurance\nAMBULANCE\nGround ambulance\nIn-network: $275 copay\nOut-of-network: $275 copay\nLimits apply\n(Ambulance|Ground ambulance)\nTHERAPY SERVICES\nOccupational therapy visit\nIn-network: $40 copay\nOut-of-network: $65 copay\nLimits apply\n(Therapy services|Occupational therapy visit)\nPhysical therapy & speech & language therapy visit\nIn-network: $40 copay\nOut-of-network: $65 copay\nLimits apply\n(Therapy services|Physical therapy & speech & language therapy visit)\nView more benefits & costs\n\n\n\n\n\n\n\n\n\nDrug Coverage\nSee if there's help to lower costs for drugs you take.\nPHARMACIES\nAdd pharmacies to get better cost estimates\nYour drug costs can change depending on your plan and pharmacy. Adding pharmacies to your account can give you better out-of-pocket cost estimates when comparing plans.\nAdd Pharmacies\nCheck the network status of each pharmacy on your list. You can change pharmacies at any time to find lower costs for drugs.\nHow do pharmacy networks affect what I pay?\nChange Pharmacies\nCOSTS BY DRUG TIER\nEach plan has a list of drugs they cover (called a \u201cformulary\u201d). Drugs on the list can be grouped into tiers with different cost levels. Some plans don\u2019t use tiers. Below is what you\u2019ll pay for drugs in each tier, based on your coverage phase.\nLearn more about drug tiers.\nTIER DRUG COST FOR\nStandard retail pharmacy drug cost for 1 month\nChange\nCOSTS BY DRUG TIER - STANDARD RETAIL PHARMACY DRUG COST FOR 1 MONTH\nBrand-name drugs\nInitial coverage phase\n25% coinsurance\nCatastrophic coverage phase\n0% coinsurance\nGeneric drugs\nInitial coverage phase\n25% coinsurance\nCatastrophic coverage phase\n0% coinsurance\nPART B DRUGS\nThese are drugs you usually get at a doctor's office or hospital outpatient setting, like the flu shot, chemotherapy, or other shots.\nPart B insulin\nIn-network: 0%-20% coinsurance\nOut-of-network: 40% coinsurance\nLimits apply\n(Part B drugs|Part B insulin)\nChemotherapy drugs\nIn-network: 0%-20% coinsurance\nOut-of-network: 40% coinsurance\nLimits apply\n(Part B drugs|Chemotherapy drugs)\nOther Part B drugs\nIn-network: 0%-20% coinsurance\nOut-of-network: 0%-40% coinsurance\nLimits apply\n(Part B drugs|Other Part B drugs)\nExtra Benefits\nHEARING\nHearing exam\nIn-network: $0 copay\nOut-of-network: $65 copay\nLimits apply\n(Hearing|Hearing exam)\nFitting/evaluation\nNot covered\nHearing aids - prescription\nIn-network: $199-$1249 copay\nOut-of-network: $199-$1249 copay\nLimits apply\n(Hearing|Hearing aids - prescription)\nHearing aids - over the counter\nIn-network: $199-$829 copay\nOut-of-network: $199-$829 copay\nLimits apply\n(Hearing|Hearing aids - over the counter)\nPREVENTIVE DENTAL\nCare to prevent or find problems with your teeth and gums.\nOral exam\nIn-network: $0 copay\nOut-of-network: $0 copay\nLimits apply\n(Preventive dental|Oral exam)\nCleaning\nIn-network: $0 copay\nOut-of-network: $0 copay\nLimits apply\n(Preventive dental|Cleaning)\nFluoride treatment\nIn-network: $0 copay\nOut-of-network: $0 copay\nLimits apply\n(Preventive dental|Fluoride treatment)\nDental x-rays\nIn-network: $0 copay\nOut-of-network: $0 copay\nLimits apply\n(Preventive dental|Dental x-rays)\nCOMPREHENSIVE DENTAL\nCare to maintain or treat problems with your teeth and gums.\nRestorative services\nIn-network: 50% coinsurance\nOut-of-network: 50% coinsurance\nLimits apply\n(Comprehensive dental|Restorative services)\nEndodontics\nIn-network: 50% coinsurance\nOut-of-network: 50% coinsurance\nLimits apply\n(Comprehensive dental|Endodontics)\nPeriodontics\nIn-network: 50% coinsurance\nOut-of-network: 50% coinsurance\nLimits apply\n(Comprehensive dental|Periodontics)\nProsthodontics, removable\nIn-network: 50% coinsurance\nOut-of-network: 50% coinsurance\nLimits apply\n(Comprehensive dental|Prosthodontics, removable)\nProsthodontics, fixed\nIn-network: 50% coinsurance\nOut-of-network: 50% coinsurance\nLimits apply\n(Comprehensive dental|Prosthodontics, fixed)\nMaxillofacial prosthetics\nIn-network: 50% coinsurance\nOut-of-network: 50% coinsurance\nLimits apply\n(Comprehensive dental|Maxillofacial prosthetics)\nImplant services\nNot covered\nOral and maxillofacial surgery\nIn-network: 50% coinsurance\nOut-of-network: 50% coinsurance\nLimits apply\n(Comprehensive dental|Oral and maxillofacial surgery)\nOrthodontics\nNot covered\nAdjunctive general services\nIn-network: 50% coinsurance\nOut-of-network: 50% coinsurance\nLimits apply\n(Comprehensive dental|Adjunctive general services)\nVISION\nRoutine eye exam\nIn-network: $0 copay\nOut-of-network: $65 copay\nLimits apply\n(Vision|Routine eye exam)\nContact lenses\nIn-network: $0 copay\nOut-of-network: $0 copay\nLimits apply\n(Vision|Contact lenses)\nEyeglasses (frames & lenses)\nNot covered\nEyeglass frames only\nIn-network: $0 copay\nOut-of-network: $0 copay\nLimits apply\n(Vision|Eyeglass frames only)\nEyeglass lenses only\nIn-network: $0-$153 copay\nOut-of-network: $0-$153 copay\nLimits apply\n(Vision|Eyeglass lenses only)\nUpgrades\nNot covered\nCollapse more extra benefits\nMEDICALLY-APPROVED NON-OPIOID PAIN MANAGEMENT SERVICES\nChiropractic services\nNot covered\nAcupuncture\nNot covered\nMassage therapy\nNot covered\nAlternative therapies\nNot covered\nMORE BENEFITS\nHealth Education\nNot covered\nCounseling Services\nNot covered\nSupport for Caregivers of Enrollees\nNot covered\nPersonal Emergency Response System (PERS)\nNot covered\nFitness benefit\nIn-network: $0 copay\nOut-of-network: $0 copay\nLimits apply\n(Preventive services|Fitness benefit)\nPlan limits - There may be limits, like the number of times you can use the item or service or how much the plan will cover. Contact the plan for details.\nTransportation services for non-emergency care: Any health-related locations\nNot covered\nTransportation services for non-emergency care: Plan-approved locations\nIn-network: $0 copay\nOut-of-network: 75% coinsurance\nLimits apply\n(Transportation|Transportation services for non-emergency care: Plan-approved locations)\nPlan limits - There may be limits, like the number of times you can use the item or service or how much the plan will cover. Contact the plan for details.\nOver the counter drug benefits\nIn-network: $0 copay\nOut-of-network: $0 copay\nLimits apply\n(Other services|Over the counter drug benefits)\nPlan limits - There may be limits, like the number of times you can use the item or service or how much the plan will cover. Contact the plan for details.\nIn-home support services\nNot covered\nHome and bathroom safety devices\nIn-network: $0 copay\nOut-of-network: $0 copay\nLimits apply\n(Preventive services|Home and bathroom safety devices)\nPlan limits - There may be limits, like the number of times you can use the item or service or how much the plan will cover. Contact the plan for details.\nMeals for short duration\nIn-network: $0 copay\nOut-of-network: $0 copay\nLimits apply\n(Other services|Meals for short duration)\nAdvanced Plan Approval Required - A process through which the physician or other health care provider is required to obtain advance approval from the plan that payment will be made for a service or item furnished to an enrollee. Unless specified otherwise with respect to a particular item or service, the enrollee is not responsible for obtaining (prior) authorization.\nPlan limits - There may be limits, like the number of times you can use the item or service or how much the plan will cover. Contact the plan for details.\nAnnual physical exams\nIn-network: $0 copay\nLimits apply\n(Preventive services|Annual physical exams)\nPlan limits - There may be limits, like the number of times you can use the item or service or how much the plan will cover. Contact the plan for details.\nTelehealth\nIn-network: $0 copay\nLimits apply\n(Professional services|Telehealth)\nPlan limits - There may be limits, like the number of times you can use the item or service or how much the plan will cover. Contact the plan for details.\nWorldwide emergency\n$0 copay\nLimits apply\n(Emergency care|Worldwide emergency)\nPlan limits - There may be limits, like the number of times you can use the item or service or how much the plan will cover. Contact the plan for details.\nPost discharge in-home medication reconciliation\nNot covered\nRe-admission prevention\nNot covered\nWigs for hair loss related to chemotherapy\nNot covered\nWeight management programs\nNot covered\nAdult day health services\nNot covered\nHome-based palliative care\nNot covered\nSPECIAL BENEFITS\nYou may get these benefits if you have a qualifying chronic condition or other factors. Contact the plan to see if you qualify before you enroll.\nFood & produce\nIn-network: $0 copay\nLimits apply\n(Chronic illness services|Food & produce)\nPlan limits - There may be limits, like the number of times you can use the item or service or how much the plan will cover. Contact the plan for details.\nMeals\nNot covered\nPest control\nNot covered\nTransportation for non-medical needs\nNot covered\nTransportation services for non-emergency care: Plan-approved locations\nNot covered\nIndoor air quality equipment and services\nNot covered\nSocial needs benefit\nNot covered\nComplementary therapies\nNot covered\nServices supporting self-direction\nNot covered\nStructural home modifications\nNot covered\nGeneral supports for living\nNot covered\nReduced cost sharing for qualifying individuals\nNot covered  \nStar Ratings\nExpand All Ratings\nOverall star rating\nOverall rating is based on the categories below.\nstars\nHealth plan star rating\nSummary rating of health plan quality\nstars\nDrug plan star rating\nSummary rating of drug plan quality\nstars\nProviders\nView Provider Network Directory\nFind participating providers\nAdd your providers to find out if they participate in this plan.\nAdd Provider\nAbout Medicare\nNondiscrimination/Accessibility\nPrivacy Policy\nPrivacy Setting\nLinking Policy\nUsing this site\nPlain Writing\nA federal government website managed and paid for by the U.S. Centers for Medicare & Medicaid Services.\n7500 Security Boulevard, Baltimore, MD 21244\n\nGive Feedback",
  "plan_info": {
    "name": "UHC Complete Care Support SC-7 (PPO C-SNP)\nUnitedHealthcare",
    "found": true,
    "organization": "UnitedHealthcare",
    "type": "Medicare Advantage with drug coverage",
    "id": "H2001-076-0"
  },
  "premiums": {
    "Total monthly premium": "$35.70",
    "Health premium": "$0.00",
    "Drug premium": "$35.70",
    "Part B premium reduction": "$What's the Part B premium reduction?"
  },
  "deductibles": {
    "Health deductible": "$0.00",
    "Drug deductible": "$615.00"
  },
  "maximum_out_of_pocket": {
    "Maximum you pay for health services": "$10,100 In and Out-of-network"
  },
  "contact_info": {
    "Plan address": "P.O. Box 30770\nSalt Lake City, UT 84130"
  },
  "benefits": {
    "Doctor Services": {
      "Primary doctor visit": "In-network: $0 copay",
      "Specialist visit": "In-network: $0-$40 copay",
      "Diagnostic tests & procedures": "In-network: $35 copay",
      "Lab services": "In-network: $0 copay",
      "Diagnostic radiology services (like MRI)": "In-network: $0-$260 copay",
      "Outpatient x-rays": "In-network: $25 copay",
      "Emergency care": "$130 copay",
      "Urgent care": "$0-$50 copay"
    },
    "Tests, Labs, & Imaging": {
      "Diagnostic tests & procedures": "In-network: $35 copay",
      "Lab services": "In-network: $0 copay",
      "Diagnostic radiology services (like MRI)": "In-network: $0-$260 copay",
      "Outpatient x-rays": "In-network: $25 copay",
      "Emergency care": "$130 copay",
      "Urgent care": "$0-$50 copay"
    },
    "Hospital Services": {
      "Inpatient hospital coverage": "In-network:",
      "Tier 1": "$455 per day for days 1-6",
      "$0 per day for days 7-90": "$0 per stay",
      "Out-of-network:": "$560 per day for days 1-19",
      "$0 per day for days 20-999": "$0 per stay",
      "Outpatient hospital coverage": "In-network: $0-$455 copay"
    },
    "Preventive Services": {
      "Preventive services": "In-network: $0 copay"
    },
    "Vision": {
      "Routine eye exam": "In-network: $0 copay",
      "Contact lenses": "In-network: $0 copay",
      "Eyeglasses (frames & lenses)": "Not covered",
      "Eyeglass frames only": "In-network: $0 copay",
      "Eyeglass lenses only": "In-network: $0-$153 copay",
      "Upgrades": "Not covered",
      "Chiropractic services": "Not covered",
      "Acupuncture": "Not covered",
      "Massage therapy": "Not covered",
      "Alternative therapies": "Not covered"
    },
    "Hearing": {
      "Hearing exam": "In-network: $0 copay",
      "Fitting/evaluation": "Not covered",
      "Hearing aids - prescription": "In-network: $199-$1249 copay",
      "Hearing aids - over the counter": "In-network: $199-$829 copay"
    },
    "Preventive Dental": {
      "Oral exam": "In-network: $0 copay",
      "Cleaning": "In-network: $0 copay",
      "Fluoride treatment": "In-network: $0 copay",
      "Dental x-rays": "In-network: $0 copay"
    },
    "Comprehensive Dental": {
      "Restorative services": "In-network: 50% coinsurance",
      "Endodontics": "In-network: 50% coinsurance",
      "Periodontics": "In-network: 50% coinsurance",
      "Prosthodontics, removable": "In-network: 50% coinsurance",
      "Prosthodontics, fixed": "In-network: 50% coinsurance",
      "Maxillofacial prosthetics": "In-network: 50% coinsurance",
      "Implant services": "Not covered",
      "Oral and maxillofacial surgery": "In-network: 50% coinsurance",
      "Orthodontics": "Not covered",
      "Adjunctive general services": "In-network: 50% coinsurance"
    },
    "Dental": {
      "Oral exam": "In-network: $0 copay",
      "Cleaning": "In-network: $0 copay",
      "Fluoride treatment": "In-network: $0 copay",
      "Dental x-rays": "In-network: $0 copay"
    },
    "Skilled Nursing Facility": {
      "Skilled nursing facility": "In-network:",
      "Tier 1": "$0 per day for days 1-20",
      "Out-of-network:": "$250 per day for days 1-100"
    }
  }
}