{
  "plan_id": "H5322_043_0",
  "scraped_at": "2025-12-09T08:17:57",
  "url": "https://www.medicare.gov/plan-compare/#/plan-details/2026-H5322-043-0?year=2026&lang=en",
  "raw_content": "An official website of the United States government\nHere's how you know\nCambiar a espa\u00f1ol\n\n\nBasics\nHealth & Drug Plans\nProviders & Services\nChat\nLog in\nBack to search results\nAARP Medicare Advantage Patriot No Rx SC-MA01 (HMO-POS)\nUnitedHealthcare\nPlan type: Medicare Advantage (without drug coverage)\nPlan ID: H5322-043-0\nPrint\nPlan website\nNon-members:\nphone number\n1-800-555-5757\nMembers:\nphone number\n1-877-370-4892\nEnroll\nWhat you'll pay\nTotal monthly premium\n$0.00\nHealth deductible\n$0.00\nPrimary doctor\n$0\ncopay\nOverview\nBenefits & Costs\nDrug Coverage\nExtra Benefits\nOptional Packages\nStar Ratings\nProviders\nOverview\nPREMIUMS\nTotal monthly premium $0.00\nHealth premium $0.00\nStandard Part B premium\nWhat's the standard Part B premium?\n$202.90\nPart B premium reduction\nWhat's the Part B premium reduction?\n\u2212$150.00 reduction\nDEDUCTIBLES\nThe amount you must pay each year before your plan starts to pay for covered services or drugs.\nHealth deductible\n$0.00\nMAXIMUM YOU PAY FOR HEALTH SERVICES\nMaximum you pay for health services\n$6,700 In-network\nCONTACT INFORMATION\nPlan address\nP.O. Box 30770\nSalt Lake City, UT 84130\nBenefits & Costs\nDOCTOR SERVICES\nView Provider Network Directory\nPrimary doctor visit In-network: $0 copay\nSpecialist visit In-network: $0-$55 copay\nLimits apply\n(Doctor services|Specialist visit)\nTESTS, LABS, & IMAGING\nDiagnostic tests & procedures\nIn-network: $50 copay\nLimits apply\n(Tests, labs, & imaging|Diagnostic tests & procedures)\nLab services In-network: $0 copay\nLimits apply\n(Tests, labs, & imaging|Lab services)\nDiagnostic radiology services (like MRI) In-network: $0-$260 copay\nLimits apply\n(Tests, labs, & imaging|Diagnostic radiology services (like MRI))\nOutpatient x-rays In-network: $30 copay\nLimits apply\n(Tests, labs, & imaging|Outpatient x-rays)\nEmergency care $130 copay\nUrgent care $0-$50 copay\nHOSPITAL SERVICES\nInpatient hospital coverage\nIn-network:\nTier 1\n$435 per day for days 1-6\n$0 per day for days 7-90\n$0 per stay\nLimits apply\n(Hospital services|Inpatient hospital coverage)\nOutpatient hospital coverage In-network: $0-$435 copay\nLimits apply\n(Hospital services|Outpatient hospital coverage)\nSKILLED NURSING FACILITY\nSkilled nursing facility\nIn-network:\nTier 1\n$0 per day for days 1-20\n$218 per day for days 21-100\nOut-of-network:\nLimits apply\n(Skilled nursing facility|Skilled nursing facility)\nPREVENTIVE SERVICES\nHealth care to prevent illness or detect illness at an early stage, when treatment is likely to work best (like Pap tests, flu shots, and screening mammograms).\nLearn more about your costs for preventive services\nPreventive services In-network: $0 copay\nAMBULANCE\nGround ambulance In-network: $275 copay\nLimits apply\n(Ambulance|Ground ambulance)\nTHERAPY SERVICES\nOccupational therapy visit In-network: $50 copay\nLimits apply\n(Therapy services|Occupational therapy visit)\nPhysical therapy & speech & language therapy visit In-network: $55 copay\nLimits apply\n(Therapy services|Physical therapy & speech & language therapy visit)\nView more benefits & costs\n\n\n\n\n\n\n\n\n\nDrug Coverage\nSee if there's help to lower costs for drugs you take.\nPART B DRUGS\nThese are drugs you usually get at a doctor's office or hospital outpatient setting, like the flu shot, chemotherapy, or other shots.\nPart B insulin In-network: 0%-20% coinsurance\nLimits apply\n(Part B drugs|Part B insulin)\nChemotherapy drugs In-network: 0%-20% coinsurance\nLimits apply\n(Part B drugs|Chemotherapy drugs)\nOther Part B drugs In-network: 0%-20% coinsurance\nLimits apply\n(Part B drugs|Other Part B drugs)\nExtra Benefits\nHEARING\nHearing exam In-network: $0 copay\nLimits apply\n(Hearing|Hearing exam)\nFitting/evaluation Not covered\nHearing aids - prescription In-network: $199-$1249 copay\nLimits apply\n(Hearing|Hearing aids - prescription)\nHearing aids - over the counter In-network: $199-$829 copay\nLimits apply\n(Hearing|Hearing aids - over the counter)\nPREVENTIVE DENTAL\nCare to prevent or find problems with your teeth and gums.\nOral exam In-network: $0 copay\nOut-of-network: $0 copay\nLimits apply\n(Preventive dental|Oral exam)\nCleaning In-network: $0 copay\nOut-of-network: $0 copay\nLimits apply\n(Preventive dental|Cleaning)\nFluoride treatment In-network: $0 copay\nOut-of-network: $0 copay\nLimits apply\n(Preventive dental|Fluoride treatment)\nDental x-rays In-network: $0 copay\nOut-of-network: $0 copay\nLimits apply\n(Preventive dental|Dental x-rays)\nCOMPREHENSIVE DENTAL\nCare to maintain or treat problems with your teeth and gums.\nRestorative services Not covered\nEndodontics Not covered\nPeriodontics Not covered\nProsthodontics, removable Not covered\nProsthodontics, fixed Not covered\nMaxillofacial prosthetics Not covered\nImplant services Not covered\nOral and maxillofacial surgery Not covered\nOrthodontics Not covered\nAdjunctive general services Not covered\nVISION\nRoutine eye exam In-network: $0 copay\nLimits apply\n(Vision|Routine eye exam)\nContact lenses In-network: $0 copay\nLimits apply\n(Vision|Contact lenses)\nEyeglasses (frames & lenses) Not covered\nEyeglass frames only In-network: $0 copay\nLimits apply\n(Vision|Eyeglass frames only)\nEyeglass lenses only In-network: $0-$153 copay\nLimits apply\n(Vision|Eyeglass lenses only)\nUpgrades Not covered\nCollapse more extra benefits\nMEDICALLY-APPROVED NON-OPIOID PAIN MANAGEMENT SERVICES\nChiropractic services Not covered\nAcupuncture Not covered\nMassage therapy Not covered\nAlternative therapies Not covered\nMORE BENEFITS\nHealth Education Not covered\nCounseling Services Not covered\nSupport for Caregivers of Enrollees Not covered\nPersonal Emergency Response System (PERS) Not covered\nFitness benefit In-network: $0 copay\nLimits apply\n(Preventive services|Fitness benefit)\nPlan limits - There may be limits, like the number of times you can use the item or service or how much the plan will cover. Contact the plan for details.\nTransportation services for non-emergency care: Any health-related locations Not covered\nTransportation services for non-emergency care: Plan-approved locations Not covered\nOver the counter drug benefits Not covered\nIn-home support services Not covered\nHome and bathroom safety devices Not covered\nMeals for short duration In-network: $0 copay\nLimits apply\n(Other services|Meals for short duration)\nAdvanced Plan Approval Required - A process through which the physician or other health care provider is required to obtain advance approval from the plan that payment will be made for a service or item furnished to an enrollee. Unless specified otherwise with respect to a particular item or service, the enrollee is not responsible for obtaining (prior) authorization.\nPlan limits - There may be limits, like the number of times you can use the item or service or how much the plan will cover. Contact the plan for details.\nAnnual physical exams In-network: $0 copay\nLimits apply\n(Preventive services|Annual physical exams)\nPlan limits - There may be limits, like the number of times you can use the item or service or how much the plan will cover. Contact the plan for details.\nTelehealth In-network: $0 copay\nLimits apply\n(Professional services|Telehealth)\nPlan limits - There may be limits, like the number of times you can use the item or service or how much the plan will cover. Contact the plan for details.\nWorldwide emergency $0 copay\nLimits apply\n(Emergency care|Worldwide emergency)\nPlan limits - There may be limits, like the number of times you can use the item or service or how much the plan will cover. Contact the plan for details.\nPost discharge in-home medication reconciliation Not covered\nRe-admission prevention Not covered\nWigs for hair loss related to chemotherapy Not covered\nWeight management programs Not covered\nAdult day health services Not covered\nHome-based palliative care Not covered\nOptional Packages\nOptional Packages\nThis plan includes optional benefits you can add to your coverage at an additional cost.\nPackage #1 Includes preventive dental services, comprehensive dental services, and pos option\nMonthly premium: $44.00\nDeductible: N/A\nStar Ratings\nExpand All Ratings\nOverall star rating\nOverall rating is based on the categories below.\nstars\nHealth plan star rating\nSummary rating of health plan quality\nstars\nProviders\nView Provider Network Directory\nFind participating providers\nAdd your providers to find out if they participate in this plan.\nAdd Provider\nAbout Medicare\nNondiscrimination/Accessibility\nPrivacy Policy\nPrivacy Setting\nLinking Policy\nUsing this site\nPlain Writing\nA federal government website managed and paid for by the U.S. Centers for Medicare & Medicaid Services.\n7500 Security Boulevard, Baltimore, MD 21244",
  "plan_info": {
    "name": "",
    "found": true,
    "organization": "UnitedHealthcare",
    "type": "Medicare Advantage (without drug coverage)",
    "id": "H5322-043-0"
  },
  "premiums": {
    "Total monthly premium": "$0.00",
    "Health premium": "$0.00",
    "Part B premium reduction": "$What's the Part B premium reduction?"
  },
  "deductibles": {
    "Health deductible": "$0.00"
  },
  "maximum_out_of_pocket": {
    "Maximum you pay for health services": "$6,700 In-network"
  },
  "contact_info": {
    "Plan address": "P.O. Box 30770\nSalt Lake City, UT 84130"
  },
  "benefits": {
    "Doctor Services": {
      "Primary doctor visit In-network: $0 copay": "Specialist visit In-network: $0-$55 copay",
      "Diagnostic tests & procedures": "In-network: $50 copay",
      "Emergency care $130 copay": "Urgent care $0-$50 copay"
    },
    "Tests, Labs, & Imaging": {
      "Diagnostic tests & procedures": "In-network: $50 copay",
      "Emergency care $130 copay": "Urgent care $0-$50 copay"
    },
    "Hospital Services": {
      "Inpatient hospital coverage": "In-network:",
      "Tier 1": "$435 per day for days 1-6",
      "$0 per day for days 7-90": "$0 per stay"
    },
    "Preventive Services": {
      "Learn more about your costs for preventive services": "Preventive services In-network: $0 copay"
    },
    "Vision": {
      "Eyeglasses (frames & lenses) Not covered": "Eyeglass frames only In-network: $0 copay"
    },
    "Hearing": {
      "Fitting/evaluation Not covered": "Hearing aids - prescription In-network: $199-$1249 copay"
    },
    "Preventive Dental": {
      "Care to prevent or find problems with your teeth and gums.": "Oral exam In-network: $0 copay",
      "Cleaning In-network: $0 copay": "Out-of-network: $0 copay",
      "Fluoride treatment In-network: $0 copay": "Out-of-network: $0 copay",
      "Dental x-rays In-network: $0 copay": "Out-of-network: $0 copay"
    },
    "Dental": {
      "Care to prevent or find problems with your teeth and gums.": "Oral exam In-network: $0 copay",
      "Cleaning In-network: $0 copay": "Out-of-network: $0 copay",
      "Fluoride treatment In-network: $0 copay": "Out-of-network: $0 copay",
      "Dental x-rays In-network: $0 copay": "Out-of-network: $0 copay"
    },
    "Skilled Nursing Facility": {
      "Skilled nursing facility": "In-network:",
      "Tier 1": "$0 per day for days 1-20"
    }
  }
}