{
  "plan_id": "H4847_007_0",
  "scraped_at": "2025-12-09T02:10:54.401464",
  "url": "https://www.medicare.gov/plan-compare/#/plan-details/2026-H4847-007-0?year=2026&lang=en",
  "raw_content": "An official website of the United States government\nHere's how you know\n\n\nMenu\nBack to search results\nWellcare Giveback (HMO-POS)\nWellcare\nPlan type: Medicare Advantage with drug coverage\nPlan ID: H4847-007-0\nPrint\nPlan website\nNon-members:\nphone number\n1-844-480-0680\nMembers:\nphone number\n1-866-892-8340\nEnroll\nWhat you'll pay\nTotal monthly premium\n$0.00\nHealth deductible\n$500\nIn-network\nPrimary doctor\n$0\ncopay\nOverview\nPREMIUMS\nTotal monthly premium\n$0.00\nHealth premium\n$0.00\nDrug premium\n$0.00\nStandard Part B premium\nWhat's the standard Part B premium?\n$202.90\nPart B premium reduction\nWhat's the Part B premium reduction?\n\u2212$55.00 reduction\nDEDUCTIBLES\nThe amount you must pay each year before your plan starts to pay for covered services or drugs.\nHealth deductible\n$500\nIn-network\nDrug deductible\n$615.00\nMAXIMUM YOU PAY FOR HEALTH SERVICES\nMaximum you pay for health services\n$9,250 In-network\nCONTACT INFORMATION\nPlan address\nPO Box 31392\nTampa, FL 33631\nBenefits & Costs\nDOCTOR SERVICES\nView Provider Network Directory\nPrimary doctor visit\nIn-network: $0 copay\nSpecialist visit\nIn-network: $50 copay\nLimits apply\n(Doctor services|Specialist visit)\nTESTS, LABS, & IMAGING\nDiagnostic tests & procedures\nIn-network: $0-$100 copay\nLimits apply\n(Tests, labs, & imaging|Diagnostic tests & procedures)\nLab services\nIn-network: $0-$50 copay\nLimits apply\n(Tests, labs, & imaging|Lab services)\nDiagnostic radiology services (like MRI)\nIn-network: $0-$350 copay\nLimits apply\n(Tests, labs, & imaging|Diagnostic radiology services (like MRI))\nOutpatient x-rays\nIn-network: $50 copay\nLimits apply\n(Tests, labs, & imaging|Outpatient x-rays)\nEmergency care\n$115 copay\nUrgent care\n$40 copay\nHOSPITAL SERVICES\nInpatient hospital coverage\nIn-network:\nTier 1\n$390 per day for days 1-6\n$0 per day for days 7-90\n$0 per stay\nLimits apply\n(Hospital services|Inpatient hospital coverage)\nOutpatient hospital coverage\nIn-network: $0-$475 copay\nLimits apply\n(Hospital services|Outpatient hospital coverage)\nSKILLED NURSING FACILITY\nSkilled nursing facility\nIn-network:\nTier 1\n$0 per day for days 1-20\n$218 per day for days 21-70\n$0 per day for days 71-100\nOut-of-network:\nLimits apply\n(Skilled nursing facility|Skilled nursing facility)\nPREVENTIVE SERVICES\nHealth care to prevent illness or detect illness at an early stage, when treatment is likely to work best (like Pap tests, flu shots, and screening mammograms).\nLearn more about your costs for preventive services\nPreventive services\nIn-network: $0 copay\nAMBULANCE\nGround ambulance\nIn-network: $350 copay\nLimits apply\n(Ambulance|Ground ambulance)\nTHERAPY SERVICES\nOccupational therapy visit\nIn-network: $35 copay\nLimits apply\n(Therapy services|Occupational therapy visit)\nPhysical therapy & speech & language therapy visit\nIn-network: $35 copay\nLimits apply\n(Therapy services|Physical therapy & speech & language therapy visit)\nView more benefits & costs\n\n\n\n\n\n\n\n\n\nDrug Coverage\nSee if there's help to lower costs for drugs you take.\nPHARMACIES\nAdd pharmacies to get better cost estimates\nYour drug costs can change depending on your plan and pharmacy. Adding pharmacies to your account can give you better out-of-pocket cost estimates when comparing plans.\nAdd Pharmacies\nCheck the network status of each pharmacy on your list. You can change pharmacies at any time to find lower costs for drugs.\nHow do pharmacy networks affect what I pay?\nChange Pharmacies\nCOSTS BY DRUG TIER\nEach plan has a list of drugs they cover (called a \u201cformulary\u201d). Drugs on the list can be grouped into tiers with different cost levels. Some plans don\u2019t use tiers. Below is what you\u2019ll pay for drugs in each tier, based on your coverage phase.\nLearn more about drug tiers.\nTIER DRUG COST FOR\nPreferred retail pharmacy drug cost for 1 month\nChange\nCOSTS BY DRUG TIER - PREFERRED RETAIL PHARMACY DRUG COST FOR 1 MONTH\nPreferred Generic\nInitial coverage phase\n$0.00 copay\nCatastrophic coverage phase\n\u2014\nGeneric\nInitial coverage phase\n$0.00 copay\nCatastrophic coverage phase\n$0 copay\nPreferred Brand\nInitial coverage phase\n25% coinsurance\nCatastrophic coverage phase\n$0 copay\nNon-Preferred Drug\nInitial coverage phase\n35% coinsurance\nCatastrophic coverage phase\n$0 copay\nSpecialty Tier\nInitial coverage phase\n25% coinsurance\nCatastrophic coverage phase\n$0 copay\nSelect Care Drugs\nInitial coverage phase\n$0.00 copay\nCatastrophic coverage phase\n$0 copay\nPART B DRUGS\nThese are drugs you usually get at a doctor's office or hospital outpatient setting, like the flu shot, chemotherapy, or other shots.\nPart B insulin\nIn-network: $35 copay\nLimits apply\n(Part B drugs|Part B insulin)\nChemotherapy drugs\nIn-network: 0%-20% coinsurance\nLimits apply\n(Part B drugs|Chemotherapy drugs)\nOther Part B drugs\nIn-network: 0%-20% coinsurance\nLimits apply\n(Part B drugs|Other Part B drugs)\nExtra Benefits\nHEARING\nHearing exam\nNot covered\nFitting/evaluation\nNot covered\nHearing aids - prescription\nNot covered\nHearing aids - over the counter\nNot covered\nPREVENTIVE DENTAL\nCare to prevent or find problems with your teeth and gums.\nOral exam\nIn-network: $0 copay\nOut-of-network: 25% coinsurance\nLimits apply\n(Preventive dental|Oral exam)\nCleaning\nIn-network: $0 copay\nOut-of-network: 25% coinsurance\nLimits apply\n(Preventive dental|Cleaning)\nFluoride treatment\nIn-network: $0 copay\nOut-of-network: 25% coinsurance\nLimits apply\n(Preventive dental|Fluoride treatment)\nDental x-rays\nIn-network: $0 copay\nOut-of-network: 25% coinsurance\nLimits apply\n(Preventive dental|Dental x-rays)\nCOMPREHENSIVE DENTAL\nCare to maintain or treat problems with your teeth and gums.\nRestorative services\nNot covered\nEndodontics\nNot covered\nPeriodontics\nNot covered\nProsthodontics, removable\nNot covered\nProsthodontics, fixed\nNot covered\nMaxillofacial prosthetics\nNot covered\nImplant services\nNot covered\nOral and maxillofacial surgery\nNot covered\nOrthodontics\nNot covered\nAdjunctive general services\nIn-network: $0 copay\nOut-of-network: 25% coinsurance\nLimits apply\n(Comprehensive dental|Adjunctive general services)\nVISION\nRoutine eye exam\nIn-network: $0 copay\nLimits apply\n(Vision|Routine eye exam)\nContact lenses\nIn-network: $0 copay\nLimits apply\n(Vision|Contact lenses)\nEyeglasses (frames & lenses)\nIn-network: $0 copay\nLimits apply\n(Vision|Eyeglasses (frames & lenses))\nEyeglass frames only\nIn-network: $0 copay\nLimits apply\n(Vision|Eyeglass frames only)\nEyeglass lenses only\nIn-network: $0 copay\nLimits apply\n(Vision|Eyeglass lenses only)\nUpgrades\nIn-network: $0 copay\nLimits apply\n(Vision|Upgrades)\nCollapse more extra benefits\nMEDICALLY-APPROVED NON-OPIOID PAIN MANAGEMENT SERVICES\nChiropractic services\nNot covered\nAcupuncture\nNot covered\nMassage therapy\nNot covered\nAlternative therapies\nIn-network: $0 copay\nLimits apply\n(Alternative therapies)\nPlan limits - There may be limits, like the number of times you can use the item or service or how much the plan will cover. Contact the plan for details.\nMORE BENEFITS\nHealth Education\nNot covered\nCounseling Services\nNot covered\nSupport for Caregivers of Enrollees\nNot covered\nPersonal Emergency Response System (PERS)\nNot covered\nFitness benefit\nIn-network: $0 copay\nLimits apply\n(Preventive services|Fitness benefit)\nPlan limits - There may be limits, like the number of times you can use the item or service or how much the plan will cover. Contact the plan for details.\nTransportation services for non-emergency care: Any health-related locations\nNot covered\nTransportation services for non-emergency care: Plan-approved locations\nNot covered\nOver the counter drug benefits\nNot covered\nIn-home support services\nNot covered\nHome and bathroom safety devices\nNot covered\nMeals for short duration\nNot covered\nAnnual physical exams\nIn-network: $0 copay\nLimits apply\n(Preventive services|Annual physical exams)\nPlan limits - There may be limits, like the number of times you can use the item or service or how much the plan will cover. Contact the plan for details.\nTelehealth\nIn-network: $0-$50 copay\nLimits apply\n(Professional services|Telehealth)\nPlan limits - There may be limits, like the number of times you can use the item or service or how much the plan will cover. Contact the plan for details.\nWorldwide emergency\n$115 copay\nLimits apply\n(Emergency care|Worldwide emergency)\nPlan limits - There may be limits, like the number of times you can use the item or service or how much the plan will cover. Contact the plan for details.\nPost discharge in-home medication reconciliation\nNot covered\nRe-admission prevention\nNot covered\nWigs for hair loss related to chemotherapy\nNot covered\nWeight management programs\nNot covered\nAdult day health services\nNot covered\nHome-based palliative care\nNot covered\nStar Ratings\nExpand All Ratings\nOverall star rating\nOverall rating is based on the categories below.\nstars\nHealth plan star rating\nSummary rating of health plan quality\nstars\nDrug plan star rating\nSummary rating of drug plan quality\nstars\nProviders\nView Provider Network Directory\nFind participating providers\nAdd your providers to find out if they participate in this plan.\nAdd Provider\nAbout Medicare\nNondiscrimination/Accessibility\nPrivacy Policy\nPrivacy Setting\nLinking Policy\nUsing this site\nPlain Writing\nA federal government website managed and paid for by the U.S. Centers for Medicare & Medicaid Services.\n7500 Security Boulevard, Baltimore, MD 21244\n\nGive Feedback",
  "plan_info": {
    "name": "Wellcare Giveback (HMO-POS)\nWellcare",
    "found": true,
    "organization": "Wellcare",
    "type": "Medicare Advantage with drug coverage",
    "id": "H4847-007-0"
  },
  "premiums": {
    "Total monthly premium": "$0.00",
    "Health premium": "$0.00",
    "Drug premium": "$0.00",
    "Part B premium reduction": "$What's the Part B premium reduction?"
  },
  "deductibles": {
    "Health deductible": "$500",
    "Drug deductible": "$615.00"
  },
  "maximum_out_of_pocket": {
    "Maximum you pay for health services": "$9,250 In-network"
  },
  "contact_info": {
    "Plan address": "PO Box 31392\nTampa, FL 33631"
  },
  "benefits": {
    "Doctor Services": {
      "Primary doctor visit": "In-network: $0 copay",
      "Specialist visit": "In-network: $50 copay",
      "Diagnostic tests & procedures": "In-network: $0-$100 copay",
      "Lab services": "In-network: $0-$50 copay",
      "Diagnostic radiology services (like MRI)": "In-network: $0-$350 copay",
      "Outpatient x-rays": "In-network: $50 copay",
      "Emergency care": "$115 copay",
      "Urgent care": "$40 copay"
    },
    "Tests, Labs, & Imaging": {
      "Diagnostic tests & procedures": "In-network: $0-$100 copay",
      "Lab services": "In-network: $0-$50 copay",
      "Diagnostic radiology services (like MRI)": "In-network: $0-$350 copay",
      "Outpatient x-rays": "In-network: $50 copay",
      "Emergency care": "$115 copay",
      "Urgent care": "$40 copay"
    },
    "Hospital Services": {
      "Inpatient hospital coverage": "In-network:",
      "Tier 1": "$390 per day for days 1-6",
      "$0 per day for days 7-90": "$0 per stay",
      "Outpatient hospital coverage": "In-network: $0-$475 copay"
    },
    "Preventive Services": {
      "Preventive services": "In-network: $0 copay"
    },
    "Vision": {
      "Routine eye exam": "In-network: $0 copay",
      "Contact lenses": "In-network: $0 copay",
      "Eyeglasses (frames & lenses)": "In-network: $0 copay",
      "Eyeglass frames only": "In-network: $0 copay",
      "Eyeglass lenses only": "In-network: $0 copay",
      "Upgrades": "In-network: $0 copay",
      "Chiropractic services": "Not covered",
      "Acupuncture": "Not covered",
      "Massage therapy": "Not covered",
      "Alternative therapies": "In-network: $0 copay"
    },
    "Hearing": {
      "Hearing exam": "Not covered",
      "Fitting/evaluation": "Not covered",
      "Hearing aids - prescription": "Not covered",
      "Hearing aids - over the counter": "Not covered"
    },
    "Preventive Dental": {
      "Oral exam": "In-network: $0 copay",
      "Cleaning": "In-network: $0 copay",
      "Fluoride treatment": "In-network: $0 copay",
      "Dental x-rays": "In-network: $0 copay"
    },
    "Comprehensive Dental": {
      "Restorative services": "Not covered",
      "Endodontics": "Not covered",
      "Periodontics": "Not covered",
      "Prosthodontics, removable": "Not covered",
      "Prosthodontics, fixed": "Not covered",
      "Maxillofacial prosthetics": "Not covered",
      "Implant services": "Not covered",
      "Oral and maxillofacial surgery": "Not covered",
      "Orthodontics": "Not covered",
      "Adjunctive general services": "In-network: $0 copay"
    },
    "Dental": {
      "Oral exam": "In-network: $0 copay",
      "Cleaning": "In-network: $0 copay",
      "Fluoride treatment": "In-network: $0 copay",
      "Dental x-rays": "In-network: $0 copay"
    },
    "Skilled Nursing Facility": {
      "Skilled nursing facility": "In-network:",
      "Tier 1": "$0 per day for days 1-20",
      "$218 per day for days 21-70": "$0 per day for days 71-100"
    }
  }
}