{
  "plan_id": "H2687_001_0",
  "scraped_at": "2025-12-09T02:01:31.660185",
  "url": "https://www.medicare.gov/plan-compare/#/plan-details/2026-H2687-001-0?year=2026&lang=en",
  "raw_content": "An official website of the United States government\nHere's how you know\n\n\nMenu\nBack to search results\nWellpoint Medicare Advantage (HMO)\nWellpoint\nPlan type: Medicare Advantage with drug coverage\nPlan ID: H2687-001-0\nPrint\nPlan website\nNon-members:\nphone number\n1-833-668-1338\nMembers:\nphone number\n1-833-613-1076\nEnroll\nWhat you'll pay\nTotal monthly premium\n$14.00\nHealth deductible\n$0.00\nPrimary doctor\n$0\ncopay\nOverview\nPREMIUMS\nTotal monthly premium\n$14.00\nHealth premium\n$0.00\nDrug premium\n$14.00\nStandard Part B premium\nWhat's the standard Part B premium?\n$202.90\nPart B premium reduction\nWhat's the Part B premium reduction?\nNot offered\nDEDUCTIBLES\nThe amount you must pay each year before your plan starts to pay for covered services or drugs.\nHealth deductible\n$0.00\nDrug deductible\n$275.00\nMAXIMUM YOU PAY FOR HEALTH SERVICES\nMaximum you pay for health services\n$9,250 In-network\nCONTACT INFORMATION\nPlan address\nAmerigroup New Jersey\n101 Wood Ave South Suite 800\nIselin, NJ 08830\nBenefits & Costs\nDOCTOR SERVICES\nView Provider Network Directory\nPrimary doctor visit\nIn-network: $0 copay\nSpecialist visit\nIn-network: $50 copay\nLimits apply\n(Doctor services|Specialist visit)\nTESTS, LABS, & IMAGING\nDiagnostic tests & procedures\nIn-network: $0-$100 copay\nLimits apply\n(Tests, labs, & imaging|Diagnostic tests & procedures)\nLab services\nIn-network: $0 copay\nLimits apply\n(Tests, labs, & imaging|Lab services)\nDiagnostic radiology services (like MRI)\nIn-network: $45-$450 copay\nLimits apply\n(Tests, labs, & imaging|Diagnostic radiology services (like MRI))\nOutpatient x-rays\nIn-network: $45-$100 copay\nLimits apply\n(Tests, labs, & imaging|Outpatient x-rays)\nEmergency care\n$115 copay\nUrgent care\n$40 copay\nHOSPITAL SERVICES\nInpatient hospital coverage\nTier 1\n$450 per day for days 1-5\n$0 per day for days 6-90\n$0 per stay\nLimits apply\n(Hospital services|Inpatient hospital coverage)\nOutpatient hospital coverage\nIn-network: $0-$375 copay\nLimits apply\n(Hospital services|Outpatient hospital coverage)\nSKILLED NURSING FACILITY\nSkilled nursing facility\nTier 1\n$0 per day for days 1-20\n$218 per day for days 21-100\nLimits apply\n(Skilled nursing facility|Skilled nursing facility)\nPREVENTIVE SERVICES\nHealth care to prevent illness or detect illness at an early stage, when treatment is likely to work best (like Pap tests, flu shots, and screening mammograms).\nLearn more about your costs for preventive services\nPreventive services\nIn-network: $0 copay\nAMBULANCE\nGround ambulance\nIn-network: $325 copay\nLimits apply\n(Ambulance|Ground ambulance)\nTHERAPY SERVICES\nOccupational therapy visit\nIn-network: $35 copay\nLimits apply\n(Therapy services|Occupational therapy visit)\nPhysical therapy & speech & language therapy visit\nIn-network: $35 copay\nLimits apply\n(Therapy services|Physical therapy & speech & language therapy visit)\nView more benefits & costs\n\n\n\n\n\n\n\n\n\nDrug Coverage\nSee if there's help to lower costs for drugs you take.\nPHARMACIES\nAdd pharmacies to get better cost estimates\nYour drug costs can change depending on your plan and pharmacy. Adding pharmacies to your account can give you better out-of-pocket cost estimates when comparing plans.\nAdd Pharmacies\nCheck the network status of each pharmacy on your list. You can change pharmacies at any time to find lower costs for drugs.\nHow do pharmacy networks affect what I pay?\nChange Pharmacies\nCOSTS BY DRUG TIER\nEach plan has a list of drugs they cover (called a \u201cformulary\u201d). Drugs on the list can be grouped into tiers with different cost levels. Some plans don\u2019t use tiers. Below is what you\u2019ll pay for drugs in each tier, based on your coverage phase.\nLearn more about drug tiers.\nTIER DRUG COST FOR\nPreferred retail pharmacy drug cost for 1 month\nChange\nCOSTS BY DRUG TIER - PREFERRED RETAIL PHARMACY DRUG COST FOR 1 MONTH\nPreferred Generic\nInitial coverage phase\n$0.00 copay\nCatastrophic coverage phase\n$0 copay\nGeneric\nInitial coverage phase\n$0.00 copay\nCatastrophic coverage phase\n$0 copay\nPreferred Brand\nInitial coverage phase\n25% coinsurance\nCatastrophic coverage phase\n$0 copay\nNon-Preferred Drug\nInitial coverage phase\n30% coinsurance\nCatastrophic coverage phase\n$0 copay\nSpecialty Tier\nInitial coverage phase\n29% coinsurance\nCatastrophic coverage phase\n$0 copay\nPART B DRUGS\nThese are drugs you usually get at a doctor's office or hospital outpatient setting, like the flu shot, chemotherapy, or other shots.\nPart B insulin\nIn-network: $35 copay\nLimits apply\n(Part B drugs|Part B insulin)\nChemotherapy drugs\nIn-network: 0%-20% coinsurance\nLimits apply\n(Part B drugs|Chemotherapy drugs)\nOther Part B drugs\nIn-network: 0%-20% coinsurance\nLimits apply\n(Part B drugs|Other Part B drugs)\nExtra Benefits\nHEARING\nHearing exam\nIn-network: $0 copay\nLimits apply\n(Hearing|Hearing exam)\nFitting/evaluation\nIn-network: $0 copay\nLimits apply\n(Hearing|Fitting/evaluation)\nHearing aids - prescription\nIn-network: $0 copay\nLimits apply\n(Hearing|Hearing aids - prescription)\nHearing aids - over the counter\nIn-network: $0 copay\nLimits apply\n(Hearing|Hearing aids - over the counter)\nPREVENTIVE DENTAL\nCare to prevent or find problems with your teeth and gums.\nOral exam\nNot covered\nCleaning\nNot covered\nFluoride treatment\nNot covered\nDental x-rays\nNot covered\nCOMPREHENSIVE DENTAL\nCare to maintain or treat problems with your teeth and gums.\nRestorative services\nNot covered\nEndodontics\nNot covered\nPeriodontics\nNot covered\nProsthodontics, removable\nNot covered\nProsthodontics, fixed\nNot covered\nMaxillofacial prosthetics\nNot covered\nImplant services\nNot covered\nOral and maxillofacial surgery\nNot covered\nOrthodontics\nNot covered\nAdjunctive general services\nNot covered\nVISION\nRoutine eye exam\nIn-network: $0 copay\nLimits apply\n(Vision|Routine eye exam)\nContact lenses\nIn-network: $0 copay\nLimits apply\n(Vision|Contact lenses)\nEyeglasses (frames & lenses)\nIn-network: $0 copay\nLimits apply\n(Vision|Eyeglasses (frames & lenses))\nEyeglass frames only\nIn-network: $0 copay\nLimits apply\n(Vision|Eyeglass frames only)\nEyeglass lenses only\nIn-network: $0 copay\nLimits apply\n(Vision|Eyeglass lenses only)\nUpgrades\nNot covered\nCollapse more extra benefits\nMEDICALLY-APPROVED NON-OPIOID PAIN MANAGEMENT SERVICES\nChiropractic services\nNot covered\nAcupuncture\nNot covered\nMassage therapy\nNot covered\nAlternative therapies\nNot covered\nMORE BENEFITS\nHealth Education\nNot covered\nCounseling Services\nNot covered\nSupport for Caregivers of Enrollees\nNot covered\nPersonal Emergency Response System (PERS)\nNot covered\nFitness benefit\nNot covered\nTransportation services for non-emergency care: Any health-related locations\nNot covered\nTransportation services for non-emergency care: Plan-approved locations\nNot covered\nOver the counter drug benefits\nNot covered\nIn-home support services\nNot covered\nHome and bathroom safety devices\nNot covered\nMeals for short duration\nIn-network: $0 copay\nLimits apply\n(Other services|Meals for short duration)\nPlan limits - There may be limits, like the number of times you can use the item or service or how much the plan will cover. Contact the plan for details.\nAnnual physical exams\nIn-network: $0 copay\nLimits apply\n(Preventive services|Annual physical exams)\nPlan limits - There may be limits, like the number of times you can use the item or service or how much the plan will cover. Contact the plan for details.\nTelehealth\nIn-network: $0 copay\nLimits apply\n(Professional services|Telehealth)\nPlan limits - There may be limits, like the number of times you can use the item or service or how much the plan will cover. Contact the plan for details.\nWorldwide emergency\n$115 copay\nLimits apply\n(Emergency care|Worldwide emergency)\nPlan limits - There may be limits, like the number of times you can use the item or service or how much the plan will cover. Contact the plan for details.\nPost discharge in-home medication reconciliation\nNot covered\nRe-admission prevention\nNot covered\nWigs for hair loss related to chemotherapy\nNot covered\nWeight management programs\nNot covered\nAdult day health services\nNot covered\nHome-based palliative care\nNot covered\nStar Ratings\nExpand All Ratings\nOverall star rating\nOverall rating is based on the categories below.\nPlan too new to be measured\nHealth plan star rating\nSummary rating of health plan quality\nPlan too new to be measured\nDrug plan star rating\nSummary rating of drug plan quality\nPlan too new to be measured\nProviders\nView Provider Network Directory\nFind participating providers\nAdd your providers to find out if they participate in this plan.\nAdd Provider\nAbout Medicare\nNondiscrimination/Accessibility\nPrivacy Policy\nPrivacy Setting\nLinking Policy\nUsing this site\nPlain Writing\nA federal government website managed and paid for by the U.S. Centers for Medicare & Medicaid Services.\n7500 Security Boulevard, Baltimore, MD 21244\n\nGive Feedback",
  "plan_info": {
    "name": "Wellpoint Medicare Advantage (HMO)\nWellpoint",
    "found": true,
    "organization": "Wellpoint",
    "type": "Medicare Advantage with drug coverage",
    "id": "H2687-001-0"
  },
  "premiums": {
    "Total monthly premium": "$14.00",
    "Health premium": "$0.00",
    "Drug premium": "$14.00",
    "Part B premium reduction": "$What's the Part B premium reduction?"
  },
  "deductibles": {
    "Health deductible": "$0.00",
    "Drug deductible": "$275.00"
  },
  "maximum_out_of_pocket": {
    "Maximum you pay for health services": "$9,250 In-network"
  },
  "contact_info": {
    "Plan address": "Amerigroup New Jersey\n101 Wood Ave South Suite 800"
  },
  "benefits": {
    "Doctor Services": {
      "Primary doctor visit": "In-network: $0 copay",
      "Specialist visit": "In-network: $50 copay",
      "Diagnostic tests & procedures": "In-network: $0-$100 copay",
      "Lab services": "In-network: $0 copay",
      "Diagnostic radiology services (like MRI)": "In-network: $45-$450 copay",
      "Outpatient x-rays": "In-network: $45-$100 copay",
      "Emergency care": "$115 copay",
      "Urgent care": "$40 copay"
    },
    "Tests, Labs, & Imaging": {
      "Diagnostic tests & procedures": "In-network: $0-$100 copay",
      "Lab services": "In-network: $0 copay",
      "Diagnostic radiology services (like MRI)": "In-network: $45-$450 copay",
      "Outpatient x-rays": "In-network: $45-$100 copay",
      "Emergency care": "$115 copay",
      "Urgent care": "$40 copay"
    },
    "Hospital Services": {
      "Inpatient hospital coverage": "Tier 1",
      "$450 per day for days 1-5": "$0 per day for days 6-90",
      "Outpatient hospital coverage": "In-network: $0-$375 copay"
    },
    "Preventive Services": {
      "Preventive services": "In-network: $0 copay"
    },
    "Vision": {
      "Routine eye exam": "In-network: $0 copay",
      "Contact lenses": "In-network: $0 copay",
      "Eyeglasses (frames & lenses)": "In-network: $0 copay",
      "Eyeglass frames only": "In-network: $0 copay",
      "Eyeglass lenses only": "In-network: $0 copay",
      "Upgrades": "Not covered",
      "Chiropractic services": "Not covered",
      "Acupuncture": "Not covered",
      "Massage therapy": "Not covered",
      "Alternative therapies": "Not covered"
    },
    "Hearing": {
      "Hearing exam": "In-network: $0 copay",
      "Fitting/evaluation": "In-network: $0 copay",
      "Hearing aids - prescription": "In-network: $0 copay",
      "Hearing aids - over the counter": "In-network: $0 copay"
    },
    "Preventive Dental": {
      "Oral exam": "Not covered",
      "Cleaning": "Not covered",
      "Fluoride treatment": "Not covered",
      "Dental x-rays": "Not covered"
    },
    "Comprehensive Dental": {
      "Restorative services": "Not covered",
      "Endodontics": "Not covered",
      "Periodontics": "Not covered",
      "Prosthodontics, removable": "Not covered",
      "Prosthodontics, fixed": "Not covered",
      "Maxillofacial prosthetics": "Not covered",
      "Implant services": "Not covered",
      "Oral and maxillofacial surgery": "Not covered",
      "Orthodontics": "Not covered",
      "Adjunctive general services": "Not covered"
    },
    "Dental": {
      "Oral exam": "Not covered",
      "Cleaning": "Not covered",
      "Fluoride treatment": "Not covered",
      "Dental x-rays": "Not covered"
    },
    "Skilled Nursing Facility": {
      "Skilled nursing facility": "Tier 1",
      "$0 per day for days 1-20": "$218 per day for days 21-100"
    }
  }
}