[
  {
    "plan_info": {
      "name": "NHC Advantage (HMO I-SNP)"
    },
    "premiums": {},
    "deductibles": {},
    "maximum_out_of_pocket": {},
    "contact_info": {},
    "benefits": {
      "Benefits & Costs": {
        "In-network: $0 copay": "Limits apply(Opioid treatment program services|Opioid treatment program services)Advanced Plan Approval Required- A process through which the physician or other health care provider is required to obtain advance approval from the plan that payment will be made for a service or item furnished to an enrollee. Unless specified otherwise with respect to a particular item or service, the enrollee is not responsible for obtaining (prior) authorization.",
        "In-network: 20% coinsurance": "",
        "$90 copay": "",
        "20% coinsurance": "",
        "Tier 1$0 per day for days 1-60$434 per day for days 61-90$868 per day for days 91-150": "Limits apply(Hospital services|Inpatient hospital coverage)Advanced Plan Approval Required- A process through which the physician or other health care provider is required to obtain advance approval from the plan that payment will be made for a service or item furnished to an enrollee. Unless specified otherwise with respect to a particular item or service, the enrollee is not responsible for obtaining (prior) authorization.",
        "$0 copay": "Limits apply(Skilled nursing facility|Skilled nursing facility)Advanced Plan Approval Required- A process through which the physician or other health care provider is required to obtain advance approval from the plan that payment will be made for a service or item furnished to an enrollee. Unless specified otherwise with respect to a particular item or service, the enrollee is not responsible for obtaining (prior) authorization.",
        "In-network: 15% coinsurance": ""
      },
      "Extra Benefits": {
        "In-network: $0 copay": "Limits apply(Other services|Over the counter drug benefits)Plan limits- There may be limits, like the number of times you can use the item or service or how much the plan will cover. Contact the plan for details.",
        "Not covered": "",
        "In-network: 0%-20% coinsurance": "Limits apply(Professional services|Telehealth)Plan limits- There may be limits, like the number of times you can use the item or service or how much the plan will cover. Contact the plan for details."
      }
    },
    "drug_coverage": {
      "25% coinsurance": "0% coinsurance",
      "In-network: 0%-20% coinsurance": "Limits apply(Part B drugs|Other Part B drugs)Advanced Plan Approval Required- A process through which the physician or other health care provider is required to obtain advance approval from the plan that payment will be made for a service or item furnished to an enrollee. Unless specified otherwise with respect to a particular item or service, the enrollee is not responsible for obtaining (prior) authorization."
    },
    "extra_benefits": {},
    "plan_id": "H4172_001_0",
    "state": "South_Carolina"
  },
  {
    "plan_id": "H4172_003_0",
    "scraped_at": "2025-12-09T02:07:59.071238",
    "url": "https://www.medicare.gov/plan-compare/#/plan-details/2026-H4172-003-0?year=2026&lang=en",
    "raw_content": "An official website of the United States government\nHere's how you know\n\n\nMenu\nBack to search results\nSenior Care (HMO I-SNP)\nNHC Advantage\nPlan type: Medicare Advantage with drug coverage\nSNP type: Institutional\nPlan ID: H4172-003-0\nPrint\nPlan website\nNon-members:\nphone number\n1-844-854-6886\nMembers:\nphone number\n1-844-854-6886\nContact plan to check eligibility\nWhat you'll pay\nTotal monthly premium\n$0.00\nHealth deductible\n$0.00\nPrimary doctor\n$0\ncopay\nOverview\nPREMIUMS\nTotal monthly premium\n$0.00\nHealth premium\n$0.00\nDrug premium\n$0.00\nStandard Part B premium\nWhat's the standard Part B premium?\n$202.90\nPart B premium reduction\nWhat's the Part B premium reduction?\nNot offered\nDEDUCTIBLES\nThe amount you must pay each year before your plan starts to pay for covered services or drugs.\nHealth deductible\n$0.00\nDrug deductible\n$250.00\nMAXIMUM YOU PAY FOR HEALTH SERVICES\nMaximum you pay for health services\n$5,000 In-network\nCONTACT INFORMATION\nPlan address\nPO Box 787\nGlen Burnie, MD 21060\nBenefits & Costs\nDOCTOR SERVICES\nView Provider Network Directory\nPrimary doctor visit\nIn-network: $0 copay\nSpecialist visit\nIn-network: $25 copay\nTESTS, LABS, & IMAGING\nDiagnostic tests & procedures\nIn-network: 20% coinsurance\nLimits apply\n(Tests, labs, & imaging|Diagnostic tests & procedures)\nLab services\nIn-network: $0 copay\nLimits apply\n(Tests, labs, & imaging|Lab services)\nDiagnostic radiology services (like MRI)\nIn-network: 20% coinsurance\nLimits apply\n(Tests, labs, & imaging|Diagnostic radiology services (like MRI))\nOutpatient x-rays\nIn-network: $0 copay\nLimits apply\n(Tests, labs, & imaging|Outpatient x-rays)\nEmergency care\n$90 copay\nUrgent care\n$40 copay\nHOSPITAL SERVICES\nInpatient hospital coverage\nTier 1\n$295 per day for days 1-6\n$0 per day for days 7-90\n$0 per stay\nLimits apply\n(Hospital services|Inpatient hospital coverage)\nOutpatient hospital coverage\nIn-network: 0%-20% coinsurance\nLimits apply\n(Hospital services|Outpatient hospital coverage)\nSKILLED NURSING FACILITY\nSkilled nursing facility\n$0 copay\nLimits apply\n(Skilled nursing facility|Skilled nursing facility)\nPREVENTIVE SERVICES\nHealth care to prevent illness or detect illness at an early stage, when treatment is likely to work best (like Pap tests, flu shots, and screening mammograms).\nLearn more about your costs for preventive services\nPreventive services\nIn-network: $0 copay\nAMBULANCE\nGround ambulance\nIn-network: $250 copay\nTHERAPY SERVICES\nOccupational therapy visit\nIn-network: $20 copay\nLimits apply\n(Therapy services|Occupational therapy visit)\nPhysical therapy & speech & language therapy visit\nIn-network: $20 copay\nLimits apply\n(Therapy services|Physical therapy & speech & language therapy visit)\nView more benefits & costs\n\n\n\n\n\n\n\n\n\nDrug Coverage\nSee if there's help to lower costs for drugs you take.\nPHARMACIES\nAdd pharmacies to get better cost estimates\nYour drug costs can change depending on your plan and pharmacy. Adding pharmacies to your account can give you better out-of-pocket cost estimates when comparing plans.\nAdd Pharmacies\nCheck the network status of each pharmacy on your list. You can change pharmacies at any time to find lower costs for drugs.\nHow do pharmacy networks affect what I pay?\nChange Pharmacies\nCOSTS BY DRUG TIER\nEach plan has a list of drugs they cover (called a \u201cformulary\u201d). Drugs on the list can be grouped into tiers with different cost levels. Some plans don\u2019t use tiers. Below is what you\u2019ll pay for drugs in each tier, based on your coverage phase.\nLearn more about drug tiers.\nTIER DRUG COST FOR\nStandard retail pharmacy drug cost for 1 month\nChange\nCOSTS BY DRUG TIER - STANDARD RETAIL PHARMACY DRUG COST FOR 1 MONTH\nPreferred Generic\nInitial coverage phase\n$2.00 copay\nCatastrophic coverage phase\n$0 copay\nGeneric\nInitial coverage phase\n$15.00 copay\nCatastrophic coverage phase\n$0 copay\nPreferred Brand\nInitial coverage phase\n$45.00 copay\nCatastrophic coverage phase\n$0 copay\nNon-Preferred Drug\nInitial coverage phase\n$95.00 copay\nCatastrophic coverage phase\n$0 copay\nSpecialty Tier\nInitial coverage phase\n30% coinsurance\nCatastrophic coverage phase\n$0 copay\nPART B DRUGS\nThese are drugs you usually get at a doctor's office or hospital outpatient setting, like the flu shot, chemotherapy, or other shots.\nPart B insulin\nIn-network: 0%-20% coinsurance\nLimits apply\n(Part B drugs|Part B insulin)\nChemotherapy drugs\nIn-network: 0%-20% coinsurance\nLimits apply\n(Part B drugs|Chemotherapy drugs)\nOther Part B drugs\nIn-network: 0%-20% coinsurance\nLimits apply\n(Part B drugs|Other Part B drugs)\nExtra Benefits\nHEARING\nHearing exam\nIn-network: $0 copay\nLimits apply\n(Hearing|Hearing exam)\nFitting/evaluation\nNot covered\nHearing aids - prescription\nIn-network: $0 copay\nHearing aids - over the counter\nNot covered\nPREVENTIVE DENTAL\nCare to prevent or find problems with your teeth and gums.\nOral exam\nIn-network: $0 copay\nLimits apply\n(Preventive dental|Oral exam)\nCleaning\nIn-network: $0 copay\nLimits apply\n(Preventive dental|Cleaning)\nFluoride treatment\nIn-network: $0 copay\nLimits apply\n(Preventive dental|Fluoride treatment)\nDental x-rays\nIn-network: $0 copay\nLimits apply\n(Preventive dental|Dental x-rays)\nCOMPREHENSIVE DENTAL\nCare to maintain or treat problems with your teeth and gums.\nRestorative services\nIn-network: $0 copay\nLimits apply\n(Comprehensive dental|Restorative services)\nEndodontics\nIn-network: $0 copay\nLimits apply\n(Comprehensive dental|Endodontics)\nPeriodontics\nIn-network: $0 copay\nLimits apply\n(Comprehensive dental|Periodontics)\nProsthodontics, removable\nIn-network: $0 copay\nLimits apply\n(Comprehensive dental|Prosthodontics, removable)\nProsthodontics, fixed\nIn-network: $0 copay\nLimits apply\n(Comprehensive dental|Prosthodontics, fixed)\nMaxillofacial prosthetics\nNot covered\nImplant services\nNot covered\nOral and maxillofacial surgery\nIn-network: $0 copay\nLimits apply\n(Comprehensive dental|Oral and maxillofacial surgery)\nOrthodontics\nNot covered\nAdjunctive general services\nIn-network: $0 copay\nLimits apply\n(Comprehensive dental|Adjunctive general services)\nVISION\nRoutine eye exam\nIn-network: $0 copay\nLimits apply\n(Vision|Routine eye exam)\nContact lenses\nIn-network: $0 copay\nLimits apply\n(Vision|Contact lenses)\nEyeglasses (frames & lenses)\nIn-network: $0 copay\nLimits apply\n(Vision|Eyeglasses (frames & lenses))\nEyeglass frames only\nIn-network: $0 copay\nLimits apply\n(Vision|Eyeglass frames only)\nEyeglass lenses only\nIn-network: $0 copay\nLimits apply\n(Vision|Eyeglass lenses only)\nUpgrades\nIn-network: $0 copay\nLimits apply\n(Vision|Upgrades)\nCollapse more extra benefits\nMEDICALLY-APPROVED NON-OPIOID PAIN MANAGEMENT SERVICES\nChiropractic services\nNot covered\nAcupuncture\nNot covered\nMassage therapy\nNot covered\nAlternative therapies\nNot covered\nMORE BENEFITS\nHealth Education\nNot covered\nCounseling Services\nNot covered\nSupport for Caregivers of Enrollees\nNot covered\nPersonal Emergency Response System (PERS)\nNot covered\nFitness benefit\nNot covered\nTransportation services for non-emergency care: Any health-related locations\nNot covered\nTransportation services for non-emergency care: Plan-approved locations\nNot covered\nOver the counter drug benefits\nIn-network: $0 copay\nLimits apply\n(Other services|Over the counter drug benefits)\nPlan limits - There may be limits, like the number of times you can use the item or service or how much the plan will cover. Contact the plan for details.\nIn-home support services\nIn-network: $0 copay\nLimits apply\n(Preventive services|In-home support services)\nPlan limits - There may be limits, like the number of times you can use the item or service or how much the plan will cover. Contact the plan for details.\nHome and bathroom safety devices\nNot covered\nMeals for short duration\nNot covered\nAnnual physical exams\nNot covered\nTelehealth\nIn-network: 0%-20% coinsurance\nLimits apply\n(Professional services|Telehealth)\nPlan limits - There may be limits, like the number of times you can use the item or service or how much the plan will cover. Contact the plan for details.\nWorldwide emergency\nNot covered\nPost discharge in-home medication reconciliation\nNot covered\nRe-admission prevention\nNot covered\nWigs for hair loss related to chemotherapy\nNot covered\nWeight management programs\nNot covered\nAdult day health services\nNot covered\nHome-based palliative care\nNot covered\nSPECIAL BENEFITS\nYou may get these benefits if you have a qualifying chronic condition or other factors. Contact the plan to see if you qualify before you enroll.\nFood & produce\nIn-network: $0 copay\nLimits apply\n(Chronic illness services|Food & produce)\nPlan limits - There may be limits, like the number of times you can use the item or service or how much the plan will cover. Contact the plan for details.\nMeals\nNot covered\nPest control\nNot covered\nTransportation for non-medical needs\nNot covered\nTransportation services for non-emergency care: Plan-approved locations\nNot covered\nIndoor air quality equipment and services\nNot covered\nSocial needs benefit\nNot covered\nComplementary therapies\nNot covered\nServices supporting self-direction\nNot covered\nStructural home modifications\nNot covered\nGeneral supports for living\nNot covered\nReduced cost sharing for qualifying individuals\nNot covered  \nStar Ratings\nExpand All Ratings\nThis plan has the highest rating. You can switch into a plan with a 5-star rating anytime during the year, even outside of an enrollment period.\nOverall star rating\nOverall rating is based on the categories below.\nThis plan got Medicare's highest rating (5 stars)\nHealth plan star rating\nSummary rating of health plan quality\nstars\nDrug plan star rating\nSummary rating of drug plan quality\nstars\nProviders\nView Provider Network Directory\nFind participating providers\nAdd your providers to find out if they participate in this plan.\nAdd Provider\nAbout Medicare\nNondiscrimination/Accessibility\nPrivacy Policy\nPrivacy Setting\nLinking Policy\nUsing this site\nPlain Writing\nA federal government website managed and paid for by the U.S. Centers for Medicare & Medicaid Services.\n7500 Security Boulevard, Baltimore, MD 21244\n\nGive Feedback",
    "plan_info": {
      "name": "Senior Care (HMO I-SNP)\nNHC Advantage",
      "found": true,
      "organization": "NHC Advantage",
      "type": "Medicare Advantage with drug coverage",
      "id": "H4172-003-0"
    },
    "premiums": {
      "Total monthly premium": "$0.00",
      "Health premium": "$0.00",
      "Drug premium": "$0.00",
      "Part B premium reduction": "$What's the Part B premium reduction?"
    },
    "deductibles": {
      "Health deductible": "$0.00",
      "Drug deductible": "$250.00"
    },
    "maximum_out_of_pocket": {
      "Maximum you pay for health services": "$5,000 In-network"
    },
    "contact_info": {
      "Plan address": "PO Box 787\nGlen Burnie, MD 21060"
    },
    "benefits": {
      "Doctor Services": {
        "Primary doctor visit": "In-network: $0 copay",
        "Specialist visit": "In-network: $25 copay",
        "Diagnostic tests & procedures": "In-network: 20% coinsurance",
        "Lab services": "In-network: $0 copay",
        "Diagnostic radiology services (like MRI)": "In-network: 20% coinsurance",
        "Outpatient x-rays": "In-network: $0 copay",
        "Emergency care": "$90 copay",
        "Urgent care": "$40 copay"
      },
      "Tests, Labs, & Imaging": {
        "Diagnostic tests & procedures": "In-network: 20% coinsurance",
        "Lab services": "In-network: $0 copay",
        "Diagnostic radiology services (like MRI)": "In-network: 20% coinsurance",
        "Outpatient x-rays": "In-network: $0 copay",
        "Emergency care": "$90 copay",
        "Urgent care": "$40 copay"
      },
      "Hospital Services": {
        "Inpatient hospital coverage": "Tier 1",
        "$295 per day for days 1-6": "$0 per day for days 7-90",
        "Outpatient hospital coverage": "In-network: 0%-20% coinsurance"
      },
      "Preventive Services": {
        "Preventive services": "In-network: $0 copay"
      },
      "Vision": {
        "Routine eye exam": "In-network: $0 copay",
        "Contact lenses": "In-network: $0 copay",
        "Eyeglasses (frames & lenses)": "In-network: $0 copay",
        "Eyeglass frames only": "In-network: $0 copay",
        "Eyeglass lenses only": "In-network: $0 copay",
        "Upgrades": "In-network: $0 copay",
        "Chiropractic services": "Not covered",
        "Acupuncture": "Not covered",
        "Massage therapy": "Not covered",
        "Alternative therapies": "Not covered"
      },
      "Hearing": {
        "Hearing exam": "In-network: $0 copay",
        "Fitting/evaluation": "Not covered",
        "Hearing aids - prescription": "In-network: $0 copay",
        "Hearing aids - over the counter": "Not covered"
      },
      "Preventive Dental": {
        "Oral exam": "In-network: $0 copay",
        "Cleaning": "In-network: $0 copay",
        "Fluoride treatment": "In-network: $0 copay",
        "Dental x-rays": "In-network: $0 copay"
      },
      "Comprehensive Dental": {
        "Restorative services": "In-network: $0 copay",
        "Endodontics": "In-network: $0 copay",
        "Periodontics": "In-network: $0 copay",
        "Prosthodontics, removable": "In-network: $0 copay",
        "Prosthodontics, fixed": "In-network: $0 copay",
        "Maxillofacial prosthetics": "Not covered",
        "Implant services": "Not covered",
        "Oral and maxillofacial surgery": "In-network: $0 copay",
        "Orthodontics": "Not covered",
        "Adjunctive general services": "In-network: $0 copay"
      },
      "Dental": {
        "Oral exam": "In-network: $0 copay",
        "Cleaning": "In-network: $0 copay",
        "Fluoride treatment": "In-network: $0 copay",
        "Dental x-rays": "In-network: $0 copay"
      },
      "Skilled Nursing Facility": {
        "Skilled nursing facility": "$0 copay"
      }
    }
  }
]